{"id":"Q101693621","type":"item","modified":"2022-10-18T15:42:57Z","labels":{"en":"Montgomery Daniel","nl":"Montgomery Daniel","ja":"モンゴメリー・ダニエル"},"claims":{"P31":[{"value":"Q5","rank":"normal","qualifiers":{}}],"P21":[{"value":"Q6581097","rank":"normal","qualifiers":{}}],"P735":[{"value":"Q1407764","rank":"normal","qualifiers":{}}],"P39":[{"value":"Q114739134","rank":"normal","qualifiers":{"P580":[{"time":"2020-12-07","timezone":0,"before":0,"after":0,"precision":11,"calendarmodel":"http://www.wikidata.org/entity/Q1985727"}],"P1365":["Q58248"]}},{"value":"Q114739529","rank":"normal","qualifiers":{"P580":[{"time":"2020-11-10","timezone":0,"before":0,"after":0,"precision":11,"calendarmodel":"http://www.wikidata.org/entity/Q1985727"}]}}],"P18":[],"P27":[],"P1559":[],"P1477":[],"P2561":[],"P734":[],"P1950":[],"P5056":[],"P2652":[],"P569":[],"P19":[],"P570":[],"P22":[],"P25":[],"P26":[],"P40":[],"P3373":[],"P69":[],"P511":[],"P102":[],"P3602":[],"P3448":[],"P451":[],"P1290":[],"P8810":[],"P1038":[]},"sitelinks":{"enwiki":"Montgomery Daniel"}}
{"id":"Q108461902","type":"item","modified":"2021-11-29T07:58:43Z","labels":{"en":"Allan Cruickshank","nl":"Allan Cruickshank"},"claims":{"P31":[{"value":"Q5","rank":"normal","qualifiers":{}}],"P21":[{"value":"Q6581097","rank":"normal","qualifiers":{}}],"P735":[{"value":"Q2616573","rank":"normal","qualifiers":{}}],"P39":[{"value":"Q19901423","rank":"normal","qualifiers":{"P580":[{"time":"1998","timezone":0,"before":0,"after":0,"precision":9,"calendarmodel":"http://www.wikidata.org/entity/Q1985727"}],"P582":[{"time":"2001","timezone":0,"before":0,"after":0,"precision":9,"calendarmodel":"http://www.wikidata.org/entity/Q1985727"}]}}],"P18":[],"P27":[],"P1559":[],"P1477":[],"P2561":[],"P734":[],"P1950":[],"P5056":[],"P2652":[],"P569":[],"P19":[],"P570":[],"P22":[],"P25":[],"P26":[],"P40":[],"P3373":[],"P69":[],"P511":[],"P102":[],"P3602":[],"P3448":[],"P451":[],"P1290":[],"P8810":[],"P1038":[]},"sitelinks":{}}
{"id":"Q108461903","type":"item","modified":"2021-12-06T18:45:00Z","labels":{"en":"Mike Browne","nl":"Mike Browne"},"claims":{"P31":[{"value":"Q5","rank":"normal","qualifiers":{}}],"P21":[{"value":"Q6581097","rank":"normal","qualifiers":{}}],"P735":[{"value":"Q361309","rank":"normal","qualifiers":{}}],"P734":[{"value":"Q991094","rank":"normal","qualifiers":{}}],"P39":[{"value":"Q19901423","rank":"normal","qualifiers":{"P580":[{"time":"2005","timezone":0,"before":0,"after":0,"precision":9,"calendarmodel":"http://www.wikidata.org/entity/Q1985727"}],"P582":[{"time":"2005","timezone":0,"before":0,"after":0,"precision":9,"calendarmodel":"http://www.wikidata.org/entity/Q1985727"}]}}],"P18":[],"P27":[],"P1559":[],"P1477":[],"P2561":[],"P1950":[],"P5056":[],"P2652":[],"P569":[],"P19":[],"P570":[],"P22":[],"P25":[],"P26":[],"P40":[],"P3373":[],"P69":[],"P511":[],"P102":[],"P3602":[],"P3448":[],"P451":[],"P1290":[],"P8810":[],"P1038":[]},"sitelinks":{}}
{"id":"Q108461905","type":"item","modified":"2021-11-06T12:51:41Z","labels":{"en":"Douglas Slater","nl":"Douglas Slater"},"claims":{"P31":[{"value":"Q5","rank":"normal","qualifiers":{}}],"P21":[{"value":"Q6581097","rank":"normal","qualifiers":{}}],"P735":[{"value":"Q463035","rank":"normal","qualifiers":{}}],"P39":[{"value":"Q19901423","rank":"normal","qualifiers":{"P580":[{"time":"2010","timezone":0,"before":0,"after":0,"precision":9,"calendarmodel":"http://www.wikidata.org/entity/Q1985727"}],"P582":[{"time":"2013","timezone":0,"before":0,"after":0,"precision":9,"calendarmodel":"http://www.wikidata.org/entity/Q1985727"}]}}],"P18":[],"P27":[],"P1559":[],"P1477":[],"P2561":[],"P734":[],"P1950":[],"P5056":[],"P2652":[],"P569":[],"P19":[],"P570":[],"P22":[],"P25":[],"P26":[],"P40":[],"P3373":[],"P69":[],"P511":[],"P102":[],"P3602":[],"P3448":[],"P451":[],"P1290":[],"P8810":[],"P1038":[]},"sitelinks":{}}
{"id":"Q114739574","type":"item","modified":"2022-11-18T07:12:54Z","labels":{"en":"Curtis King"},"claims":{"P31":[{"value":"Q5","rank":"normal","qualifiers":{}}],"P21":[{"value":"Q6581097","rank":"normal","qualifiers":{}}],"P39":[{"value":"Q114739112","rank":"normal","qualifiers":{"P580":[{"time":"2020-11-10","timezone":0,"before":0,"after":0,"precision":11,"calendarmodel":"http://www.wikidata.org/entity/Q1985727"}]}}],"P18":[],"P27":[],"P1559":[],"P1477":[],"P2561":[],"P735":[],"P734":[],"P1950":[],"P5056":[],"P2652":[],"P569":[],"P19":[],"P570":[],"P22":[],"P25":[],"P26":[],"P40":[],"P3373":[],"P69":[],"P511":[],"P102":[],"P3602":[],"P3448":[],"P451":[],"P1290":[],"P8810":[],"P1038":[]},"sitelinks":{}}
{"id":"Q114739575","type":"item","modified":"2022-10-18T15:48:33Z","labels":{"en":"Frederick Stephenson"},"claims":{"P31":[{"value":"Q5","rank":"normal","qualifiers":{}}],"P21":[{"value":"Q6581097","rank":"normal","qualifiers":{}}],"P39":[{"value":"Q114739522","rank":"normal","qualifiers":{"P580":[{"time":"2020-11-10","timezone":0,"before":0,"after":0,"precision":11,"calendarmodel":"http://www.wikidata.org/entity/Q1985727"}]}}],"P18":[],"P27":[],"P1559":[],"P1477":[],"P2561":[],"P735":[],"P734":[],"P1950":[],"P5056":[],"P2652":[],"P569":[],"P19":[],"P570":[],"P22":[],"P25":[],"P26":[],"P40":[],"P3373":[],"P69":[],"P511":[],"P102":[],"P3602":[],"P3448":[],"P451":[],"P1290":[],"P8810":[],"P1038":[]},"sitelinks":{}}
{"id":"Q114739576","type":"item","modified":"2022-10-18T15:48:35Z","labels":{"en":"Julian Francis"},"claims":{"P31":[{"value":"Q5","rank":"normal","qualifiers":{}}],"P21":[{"value":"Q6581097","rank":"normal","qualifiers":{}}],"P39":[{"value":"Q114739537","rank":"normal","qualifiers":{"P580":[{"time":"2020-11-10","timezone":0,"before":0,"after":0,"precision":11,"calendarmodel":"http://www.wikidata.org/entity/Q1985727"}]}}],"P18":[],"P27":[],"P1559":[],"P1477":[],"P2561":[],"P735":[],"P734":[],"P1950":[],"P5056":[],"P2652":[],"P569":[],"P19":[],"P570":[],"P22":[],"P25":[],"P26":[],"P40":[],"P3373":[],"P69":[],"P511":[],"P102":[],"P3602":[],"P3448":[],"P451":[],"P1290":[],"P8810":[],"P1038":[]},"sitelinks":{}}
{"id":"Q114739577","type":"item","modified":"2022-10-18T15:48:30Z","labels":{"en":"Orando Brewster"},"claims":{"P31":[{"value":"Q5","rank":"normal","qualifiers":{}}],"P21":[{"value":"Q6581097","rank":"normal","qualifiers":{}}],"P39":[{"value":"Q114739231","rank":"normal","qualifiers":{"P580":[{"time":"2020-11-10","timezone":0,"before":0,"after":0,"precision":11,"calendarmodel":"http://www.wikidata.org/entity/Q1985727"}]}}],"P18":[],"P27":[],"P1559":[],"P1477":[],"P2561":[],"P735":[],"P734":[],"P1950":[],"P5056":[],"P2652":[],"P569":[],"P19":[],"P570":[],"P22":[],"P25":[],"P26":[],"P40":[],"P3373":[],"P69":[],"P511":[],"P102":[],"P3602":[],"P3448":[],"P451":[],"P1290":[],"P8810":[],"P1038":[]},"sitelinks":{}}
{"id":"Q114740002","type":"item","modified":"2022-11-18T07:11:21Z","labels":{"en":"Jaundy Martin"},"claims":{"P31":[{"value":"Q5","rank":"normal","qualifiers":{}}],"P21":[{"value":"Q6581097","rank":"normal","qualifiers":{}}],"P39":[{"value":"Q114740003","rank":"normal","qualifiers":{"P580":[{"time":"2017-09-18","timezone":0,"before":0,"after":0,"precision":11,"calendarmodel":"http://www.wikidata.org/entity/Q1985727"}],"P582":[{"time":"2022-11-01","timezone":0,"before":0,"after":0,"precision":11,"calendarmodel":"http://www.wikidata.org/entity/Q1985727"}],"P1366":["Q115263413"]}}],"P18":[],"P27":[],"P1559":[],"P1477":[],"P2561":[],"P735":[],"P734":[],"P1950":[],"P5056":[],"P2652":[],"P569":[],"P19":[],"P570":[],"P22":[],"P25":[],"P26":[],"P40":[],"P3373":[],"P69":[],"P511":[],"P102":[],"P3602":[],"P3448":[],"P451":[],"P1290":[],"P8810":[],"P1038":[]},"sitelinks":{}}
{"id":"Q115263405","type":"item","modified":"2022-11-28T21:50:16Z","labels":{"en":"Keisal Peters","pt":"Keisal Peters","pt-br":"Keisal Peters"},"claims":{"P31":[{"value":"Q5","rank":"normal","qualifiers":{}}],"P21":[{"value":"Q6581072","rank":"normal","qualifiers":{}}],"P39":[{"value":"Q19901423","rank":"normal","qualifiers":{"P580":[{"time":"2022-08-16","timezone":0,"before":0,"after":0,"precision":11,"calendarmodel":"http://www.wikidata.org/entity/Q1985727"}],"P1365":["Q57800"]}}],"P18":[],"P27":[],"P1559":[],"P1477":[],"P2561":[],"P735":[],"P734":[],"P1950":[],"P5056":[],"P2652":[],"P569":[],"P19":[],"P570":[],"P22":[],"P25":[],"P26":[],"P40":[],"P3373":[],"P69":[],"P511":[],"P102":[],"P3602":[],"P3448":[],"P451":[],"P1290":[],"P8810":[],"P1038":[]},"sitelinks":{}}
{"id":"Q115263413","type":"item","modified":"2022-11-18T07:19:09Z","labels":{"en":"Grenville T Williams"},"claims":{"P31":[{"value":"Q5","rank":"normal","qualifiers":{}}],"P21":[{"value":"Q6581097","rank":"normal","qualifiers":{}}],"P39":[{"value":"Q114740003","rank":"normal","qualifiers":{"P580":[{"time":"2022-11-01","timezone":0,"before":0,"after":0,"precision":11,"calendarmodel":"http://www.wikidata.org/entity/Q1985727"}],"P1365":["Q114740002"]}}],"P18":[],"P27":[],"P1559":[],"P1477":[],"P2561":[],"P735":[],"P734":[],"P1950":[],"P5056":[],"P2652":[],"P569":[],"P19":[],"P570":[],"P22":[],"P25":[],"P26":[],"P40":[],"P3373":[],"P69":[],"P511":[],"P102":[],"P3602":[],"P3448":[],"P451":[],"P1290":[],"P8810":[],"P1038":[]},"sitelinks":{}}
{"id":"Q1268324","type":"item","modified":"2022-10-18T14:48:26Z","labels":{"pl":"Arnhim Eustace","el":"Άρνχιμ Γιούστας","ru":"Юстас, Арним","sh":"Arnhim Eustace","en":"Arnhim Eustace","es":"Arnhim Eustace","nl":"Arnhim Eustace","de":"Arnhim Eustace","zh-hant":"亞辛·尤斯塔斯","zh-cn":"亚辛·尤斯塔斯","ja":"アーニム・ユースタス","sl":"Arnhim Eustace","zh-hans":"亚辛·尤斯塔斯","ast":"Arnhim Eustace","fa":"آرنهیم یوستاس","zh":"亚辛·尤斯塔斯","fr":"Arnhim Eustace","sq":"Arnhim Eustace","arz":"ارنهيم اوستاس"},"claims":{"P31":[{"value":"Q5","rank":"normal","qualifiers":{}}],"P18":[{"value":"Arnhim Eustace.jpg","rank":"normal","qualifiers":{}}],"P21":[{"value":"Q6581097","rank":"normal","qualifiers":{}}],"P27":[{"value":"Q757","rank":"normal","qualifiers":{}}],"P1559":[{"value":{"text":"Arnhim Ulric Eustace","language":"en"},"rank":"normal","qualifiers":{}}],"P734":[{"value":"Q18915237","rank":"normal","qualifiers":{}}],"P569":[{"value":{"time":"1944-10-05","timezone":0,"before":0,"after":0,"precision":11,"calendarmodel":"http://www.wikidata.org/entity/Q1985727"},"rank":"normal","qualifiers":{}}],"P19":[{"value":"Q2660774","rank":"normal","qualifiers":{}}],"P39":[{"value":"Q30101507","rank":"normal","qualifiers":{"P580":[{"time":"2000-10-27","timezone":0,"before":0,"after":0,"precision":11,"calendarmodel":"http://www.wikidata.org/entity/Q1985727"}],"P582":[{"time":"2001-03-29","timezone":0,"before":0,"after":0,"precision":11,"calendarmodel":"http://www.wikidata.org/entity/Q1985727"}],"P1365":["Q1281056"],"P1366":["Q57800"]}}],"P69":[{"value":"Q2065769","rank":"normal","qualifiers":{}},{"value":"Q15277924","rank":"normal","qualifiers":{}}],"P102":[{"value":"Q1255291","rank":"normal","qualifiers":{}}],"P1477":[],"P2561":[],"P735":[],"P1950":[],"P5056":[],"P2652":[],"P570":[],"P22":[],"P25":[],"P26":[],"P40":[],"P3373":[],"P511":[],"P3602":[],"P3448":[],"P451":[],"P1290":[],"P8810":[],"P1038":[]},"sitelinks":{"arzwiki":"ارنهيم اوستاس","commonswiki":"Category:Arnhim Eustace","dewiki":"Arnhim Ulric Eustace","elwiki":"Άρνχιμ Γιούστας","enwiki":"Arnhim Eustace","eswiki":"Arnhim Eustace","fawiki":"آرنهیم یوستاس","frwiki":"Arnhim Eustace","plwiki":"Arnhim Eustace","ruwiki":"Юстас, Арним","shwiki":"Arnhim Eustace","simplewiki":"Arnhim Eustace"}}
{"id":"Q1281056","type":"item","modified":"2022-10-05T01:57:05Z","labels":{"de":"James Fitz-Allen Mitchell","el":"Τζέιμς Φιτς-Άλεν Μίτσελ","ru":"Митчелл, Джеймс Фитц-Аллен","fr":"James Fitz-Allen Mitchell","sh":"James Fitz-Allen Mitchell","en":"James Fitz-Allen Mitchell","nl":"James Fitz-Allen Mitchell","es":"James Fitz-Allen Mitchell","nb":"James Fitz-Allen Mitchell","da":"James Fitz-Allen Mitchell","nn":"James Fitz-Allen Mitchell","sv":"James Fitz-Allen Mitchell","hu":"James Fitz-Allen Mitchell","zh-hant":"詹姆斯·菲茨-艾倫·米切爾","zh-cn":"詹姆斯·菲茨-艾伦·米切尔","ja":"ジェームズ・フィッツ＝アレン・ミッチェル","sl":"James Fitz-Allen Mitchell","zh-hans":"詹姆斯·菲茨-艾伦·米切尔","zh":"詹姆斯·菲茨-艾倫·米切爾","ast":"James Fitz-Allen Mitchell","fa":"جیمز فیتز-آلن میچل","sq":"James Fitz-Allen Mitchell","tr":"James Fitz-Allen Mitchell","eu":"James Fitz-Allan Mitchell","id":"James Fitz-Allen Mitchell"},"claims":{"P31":[{"value":"Q5","rank":"normal","qualifiers":{}}],"P18":[{"value":"James F. Mitchell 1986 (cropped).jpg","rank":"normal","qualifiers":{"P585":[{"time":"1986-02-20","timezone":0,"before":0,"after":0,"precision":11,"calendarmodel":"http://www.wikidata.org/entity/Q1985727"}]}}],"P21":[{"value":"Q6581097","rank":"normal","qualifiers":{}}],"P27":[{"value":"Q757","rank":"normal","qualifiers":{}}],"P1559":[{"value":{"text":"James Fitz-Allen Mitchell","language":"en"},"rank":"normal","qualifiers":{}}],"P735":[{"value":"Q677191","rank":"normal","qualifiers":{}}],"P734":[{"value":"Q179205","rank":"normal","qualifiers":{}}],"P569":[{"value":{"time":"1931-05-15","timezone":0,"before":0,"after":0,"precision":11,"calendarmodel":"http://www.wikidata.org/entity/Q1985727"},"rank":"normal","qualifiers":{}}],"P19":[{"value":"Q257857","rank":"normal","qualifiers":{"P131":["Q2660774"],"P17":["Q8680"]}}],"P570":[{"value":{"time":"2021-11-23","timezone":0,"before":0,"after":0,"precision":11,"calendarmodel":"http://www.wikidata.org/entity/Q1985727"},"rank":"normal","qualifiers":{}}],"P39":[{"value":"Q30101507","rank":"normal","qualifiers":{"P580":[{"time":"1984-07-30","timezone":0,"before":0,"after":0,"precision":11,"calendarmodel":"http://www.wikidata.org/entity/Q1985727"}],"P582":[{"time":"2000-10-27","timezone":0,"before":0,"after":0,"precision":11,"calendarmodel":"http://www.wikidata.org/entity/Q1985727"}],"P1365":["Q165402"],"P1366":["Q1268324"]}}],"P102":[{"value":"Q1255291","rank":"normal","qualifiers":{}}],"P1477":[],"P2561":[],"P1950":[],"P5056":[],"P2652":[],"P22":[],"P25":[],"P26":[],"P40":[],"P3373":[],"P69":[],"P511":[],"P3602":[],"P3448":[],"P451":[],"P1290":[],"P8810":[],"P1038":[]},"sitelinks":{"commonswiki":"Category:James Fitz-Allen Mitchell","dewiki":"James Fitz-Allen Mitchell","elwiki":"Τζέιμς Φιτς-Άλεν Μίτσελ","enwiki":"James Fitz-Allen Mitchell","eswiki":"James Fitz-Allen Mitchell","euwiki":"James Fitz-Allen Mitchell","fawiki":"جیمز فیتز-آلن میچل","frwiki":"James Fitz-Allen Mitchell","idwiki":"James Fitz-Allen Mitchell","ruwiki":"Митчелл, Джеймс Фитц-Аллен","shwiki":"James Fitz-Allen Mitchell","simplewiki":"James Fitz-Allen Mitchell","trwiki":"James Fitz-Allen Mitchell","zhwiki":"詹姆斯·菲茨-艾伦·米切尔"}}
{"id":"Q28382039","type":"item","modified":"2022-10-18T15:31:29Z","labels":{"de":"St. Clair Prince","nl":"St. Clair Prince","en":"St. Clair Prince","ast":"St. Clair Prince"},"claims":{"P31":[{"value":"Q5","rank":"normal","qualifiers":{}}],"P21":[{"value":"Q6581097","rank":"normal","qualifiers":{}}],"P27":[{"value":"Q757","rank":"normal","qualifiers":{}}],"P569":[{"value":{"time":"1950","timezone":0,"before":0,"after":0,"precision":7,"calendarmodel":"http://www.wikidata.org/entity/Q1985727"},"rank":"normal","qualifiers":{}}],"P39":[{"value":"Q114739223","rank":"normal","qualifiers":{"P580":[{"time":"2020-11-10","timezone":0,"before":0,"after":0,"precision":11,"calendarmodel":"http://www.wikidata.org/entity/Q1985727"}]}}],"P18":[],"P1559":[],"P1477":[],"P2561":[],"P735":[],"P734":[],"P1950":[],"P5056":[],"P2652":[],"P19":[],"P570":[],"P22":[],"P25":[],"P26":[],"P40":[],"P3373":[],"P69":[],"P511":[],"P102":[],"P3602":[],"P3448":[],"P451":[],"P1290":[],"P8810":[],"P1038":[]},"sitelinks":{"dewiki":"St. Clair Prince"}}
{"id":"Q28382042","type":"item","modified":"2022-10-18T15:33:37Z","labels":{"de":"Carlos James","nl":"Carlos James","en":"Carlos James","ast":"Carlos James","es":"Carlos James"},"claims":{"P31":[{"value":"Q5","rank":"normal","qualifiers":{}}],"P21":[{"value":"Q6581097","rank":"normal","qualifiers":{}}],"P27":[{"value":"Q757","rank":"normal","qualifiers":{}}],"P735":[{"value":"Q364753","rank":"normal","qualifiers":{}}],"P734":[{"value":"Q12188082","rank":"normal","qualifiers":{}}],"P569":[{"value":{"time":"1950","timezone":0,"before":0,"after":0,"precision":7,"calendarmodel":"http://www.wikidata.org/entity/Q1985727"},"rank":"normal","qualifiers":{}}],"P39":[{"value":"Q21296452","rank":"normal","qualifiers":{}},{"value":"Q114739528","rank":"normal","qualifiers":{"P580":[{"time":"2020-11-10","timezone":0,"before":0,"after":0,"precision":11,"calendarmodel":"http://www.wikidata.org/entity/Q1985727"}]}}],"P18":[],"P1559":[],"P1477":[],"P2561":[],"P1950":[],"P5056":[],"P2652":[],"P19":[],"P570":[],"P22":[],"P25":[],"P26":[],"P40":[],"P3373":[],"P69":[],"P511":[],"P102":[],"P3602":[],"P3448":[],"P451":[],"P1290":[],"P8810":[],"P1038":[]},"sitelinks":{"dewiki":"Carlos James"}}
{"id":"Q354705","type":"item","modified":"2022-11-16T16:01:19Z","labels":{"pt":"Frederick Ballantyne","zh-hans":"弗雷德里克·巴兰坦","zh-hant":"弗雷德里克·巴蘭坦","zh-hk":"弗雷德里克·巴蘭坦","zh-cn":"弗雷德里克·巴兰坦","zh-sg":"弗雷德里克·巴兰坦","zh-tw":"弗雷德里克·巴蘭坦","pl":"Frederick Ballantyne","ko":"프레드릭 밸런타인","ru":"Фредерик Баллантайн","fr":"Frederick Ballantyne","en":"Frederick Ballantyne","es":"Frederick Ballantyne","tr":"Frederick Ballantyne","yo":"Frederick Ballantyne","fi":"Frederick Ballantyne","it":"Frederick Ballantyne","et":"Frederick Ballantyne","id":"Frederick Ballantyne","de":"Frederick Ballantyne","ja":"フレデリック・バランタイン","el":"Φρέντερικ Μπάλανταϊν","nb":"Frederick Ballantyne","sv":"Frederick Ballantyne","nl":"Frederick Ballantyne","zh":"弗雷德里克·巴兰坦","lt":"Frederick Ballantyne","fa":"فردریک بلنتاین","da":"Frederick Ballantyne","nn":"Frederick Ballantyne","hu":"Frederick Ballantyne","bar":"Frederick Ballantyne","hi":"फ्रेडरिक बॅलंटाइन","uk":"Фредерік Баллантайн","sl":"Frederick Ballantyne","pt-br":"Frederick Ballantyne","ast":"Frederick Ballantyne","eu":"Frederick Ballantyne"},"claims":{"P31":[{"value":"Q5","rank":"normal","qualifiers":{}}],"P18":[{"value":"Frederick Ballantyne (cropped).jpg","rank":"normal","qualifiers":{}}],"P21":[{"value":"Q6581097","rank":"normal","qualifiers":{}}],"P27":[{"value":"Q757","rank":"normal","qualifiers":{}}],"P1559":[{"value":{"text":"Sir Frederick Nathaniel Ballantyne","language":"en"},"rank":"normal","qualifiers":{}}],"P735":[{"value":"Q3273004","rank":"normal","qualifiers":{}}],"P734":[{"value":"Q21493425","rank":"normal","qualifiers":{}}],"P569":[{"value":{"time":"1936-07-05","timezone":0,"before":0,"after":0,"precision":11,"calendarmodel":"http://www.wikidata.org/entity/Q1985727"},"rank":"normal","qualifiers":{}}],"P19":[{"value":"Q2630835","rank":"normal","qualifiers":{}}],"P570":[{"value":{"time":"2020-01-23","timezone":0,"before":0,"after":0,"precision":11,"calendarmodel":"http://www.wikidata.org/entity/Q1985727"},"rank":"normal","qualifiers":{}}],"P39":[{"value":"Q61037457","rank":"normal","qualifiers":{"P580":[{"time":"2002-09-02","timezone":0,"before":0,"after":0,"precision":11,"calendarmodel":"http://www.wikidata.org/entity/Q1985727"}],"P1365":["Q6899931"],"P582":[{"time":"2019-08-01","timezone":0,"before":0,"after":0,"precision":11,"calendarmodel":"http://www.wikidata.org/entity/Q1985727"}]}},{"value":"Q3504856","rank":"normal","qualifiers":{}}],"P69":[{"value":"Q617433","rank":"normal","qualifiers":{}},{"value":"Q3297997","rank":"normal","qualifiers":{}},{"value":"Q1068752","rank":"normal","qualifiers":{}}],"P1477":[],"P2561":[],"P1950":[],"P5056":[],"P2652":[],"P22":[],"P25":[],"P26":[],"P40":[],"P3373":[],"P511":[],"P102":[],"P3602":[],"P3448":[],"P451":[],"P1290":[],"P8810":[],"P1038":[]},"sitelinks":{"barwiki":"Frederick Ballantyne","commonswiki":"Category:Frederick Ballantyne","dewiki":"Frederick Ballantyne","elwiki":"Φρέντερικ Μπάλανταϊν","enwiki":"Frederick Ballantyne","eswiki":"Frederick Ballantyne","etwiki":"Frederick Ballantyne","euwiki":"Frederick Ballantyne","fawiki":"فردریک بلنتاین","fiwiki":"Frederick Ballantyne","frwiki":"Frederick Ballantyne","hiwiki":"फ्रेडरिक बॅलंटाइन","idwiki":"Frederick Ballantyne","itwiki":"Frederick Ballantyne","jawiki":"フレデリック・バランタイン","kowiki":"프레드릭 밸런타인","ltwiki":"Frederick Ballantyne","nowiki":"Frederick Ballantyne","plwiki":"Frederick Ballantyne","ptwiki":"Frederick Ballantyne","ruwiki":"Баллантайн, Фредерик","simplewiki":"Frederick Ballantyne","trwiki":"Frederick Ballantyne","ukwiki":"Фредерік Баллантайн","yowiki":"Frederick Ballantyne","zhwiki":"弗雷德里克·巴兰坦"}}
{"id":"Q3560964","type":"item","modified":"2022-10-18T14:04:45Z","labels":{"pl":"Charles Antrobus","el":"Τσαρλς Άντρομπας","en":"Charles Antrobus","fi":"Charles Antrobus","es":"Charles Antrobus","nl":"Charles Antrobus","de":"Charles Antrobus","cy":"Charles Antrobus","hu":"Charles Antrobus","fr":"Charles Antrobus","ja":"チャールズ・アントロバス","hi":"चार्ल्स ऍञ्ट्रोबस","zh":"安卓巴斯","ast":"Charles Antrobus","fa":"چارلز آنتروباس","uk":"Чарльз Антробус","ru":"Антробус, Чарльз"},"claims":{"P31":[{"value":"Q5","rank":"normal","qualifiers":{}}],"P21":[{"value":"Q6581097","rank":"normal","qualifiers":{}}],"P27":[{"value":"Q757","rank":"normal","qualifiers":{}}],"P735":[{"value":"Q2958359","rank":"normal","qualifiers":{}}],"P569":[{"value":{"time":"1933-05-14","timezone":0,"before":0,"after":0,"precision":11,"calendarmodel":"http://www.wikidata.org/entity/Q1985727"},"rank":"normal","qualifiers":{}}],"P19":[{"value":"Q379656","rank":"normal","qualifiers":{}}],"P570":[{"value":{"time":"2002-06-03","timezone":0,"before":0,"after":0,"precision":11,"calendarmodel":"http://www.wikidata.org/entity/Q1985727"},"rank":"normal","qualifiers":{}}],"P39":[{"value":"Q61037457","rank":"normal","qualifiers":{}},{"value":"Q61037457","rank":"normal","qualifiers":{"P580":[{"time":"1996-06-01","timezone":0,"before":0,"after":0,"precision":11,"calendarmodel":"http://www.wikidata.org/entity/Q1985727"}],"P582":[{"time":"2002-06-03","timezone":0,"before":0,"after":0,"precision":11,"calendarmodel":"http://www.wikidata.org/entity/Q1985727"}]}}],"P18":[],"P1559":[],"P1477":[],"P2561":[],"P734":[],"P1950":[],"P5056":[],"P2652":[],"P22":[],"P25":[],"P26":[],"P40":[],"P3373":[],"P69":[],"P511":[],"P102":[],"P3602":[],"P3448":[],"P451":[],"P1290":[],"P8810":[],"P1038":[]},"sitelinks":{"dewiki":"Charles Antrobus","elwiki":"Τσαρλς Άντρομπας","enwiki":"Charles Antrobus","fawiki":"چارلز آنتروباس","fiwiki":"Charles Antrobus","hiwiki":"चार्ल्स ऍञ्ट्रोबस","plwiki":"Charles Antrobus","ruwiki":"Антробус, Чарльз","ukwiki":"Чарльз Антробус"}}
{"id":"Q42386929","type":"item","modified":"2022-10-18T15:31:33Z","labels":{"en":"Saboto Caesar","nl":"Saboto Caesar","es":"Saboto Caesar","ast":"Saboto Caesar","sq":"Saboto Caesar"},"claims":{"P31":[{"value":"Q5","rank":"normal","qualifiers":{}}],"P18":[{"value":"Saboto Caesar (cropped).jpg","rank":"normal","qualifiers":{"P585":[{"time":"2022-04-20","timezone":0,"before":0,"after":0,"precision":11,"calendarmodel":"http://www.wikidata.org/entity/Q1985727"}]}}],"P21":[{"value":"Q6581097","rank":"normal","qualifiers":{}}],"P569":[{"value":{"time":"1980-12-21","timezone":0,"before":0,"after":0,"precision":11,"calendarmodel":"http://www.wikidata.org/entity/Q1985727"},"rank":"normal","qualifiers":{}}],"P19":[{"value":"Q757","rank":"normal","qualifiers":{}}],"P39":[{"value":"Q114739220","rank":"normal","qualifiers":{"P580":[{"time":"2020-11-10","timezone":0,"before":0,"after":0,"precision":11,"calendarmodel":"http://www.wikidata.org/entity/Q1985727"}]}}],"P102":[{"value":"Q1277617","rank":"normal","qualifiers":{}}],"P27":[],"P1559":[],"P1477":[],"P2561":[],"P735":[],"P734":[],"P1950":[],"P5056":[],"P2652":[],"P570":[],"P22":[],"P25":[],"P26":[],"P40":[],"P3373":[],"P69":[],"P511":[],"P3602":[],"P3448":[],"P451":[],"P1290":[],"P8810":[],"P1038":[]},"sitelinks":{"enwiki":"Saboto Caesar"}}
{"id":"Q43274","type":"item","modified":"2023-01-09T12:13:58Z","labels":{"zh":"查尔斯三世","eu":"Karlos III.a Erresuma Batukoa","pl":"Karol III","gd":"Teàrlach III","bs":"Charles III","ang":"Carl III","es":"Carlos III del Reino Unido","ta":"வேல்சு இளவரசர் சார்லசு","af":"Charles III van die Verenigde Koninkryk","oc":"Carles Windsor","ms":"Charles III","hu":"III. Károly brit király","et":"Charles III","el":"Κάρολος Γ΄ του Ηνωμένου Βασιλείου","ga":"Séarlas, Prionsa na Breataine Bige","my":"ချားလ်စ် ဝေလမင်းသား","pnb":"شہزادہ چارلس","kw":"Charlys, Pryns Kembra","ar":"تشارلز الثالث","sv":"Charles III","nl":"Charles III van het Verenigd Koninkrijk","pt":"Carlos III do Reino Unido","is":"Karl 3. Bretakonungur","eo":"Karlo la 3-a","ru":"Карл III","sr":"Чарлс, принц од Велса","tr":"III. Charles","se":"Charles","mk":"Чарлс III","fi":"Charles III","uk":"Чарльз III","nn":"Kong Charles III av Storbritannia","gu":"પ્રિન્સ ચાર્લ્સ","sco":"The Prince Charles, Duke o Rothesay","az":"III Çarlz","hr":"Charles III.","da":"Charles 3. af Storbritannien","fr":"Charles III","ko":"찰스 3세","he":"צ'ארלס השלישי, מלך הממלכה המאוחדת","be":"Карл III","arz":"تشارلز التالت","lv":"Čārlzs III","it":"Carlo III del Regno Unito","gl":"Carlos de Inglaterra","de":"Charles III.","id":"Charles III dari Britania Raya","ja":"チャールズ3世","yue":"查理斯三世","en":"Charles III","hi":"चार्ल्स","mn":"Уэльсийн хунтайж Чарльз","hy":"Չարլզ, Ուելսի արքայազն","th":"สมเด็จพระเจ้าชาลส์ที่ 3 แห่งสหราชอาณาจักร","ro":"Charles al III-lea","ca":"Carles III del Regne Unit","la":"Carolus III (rex Britanniarum)","cy":"Siarl III","war":"Karlos III","sl":"Karel III.","cs":"Karel III. Britský","bg":"Чарлз III","mr":"वेल्सचा युवराज चार्ल्स","fa":"چارلز، شاهزاده ولز","te":"చార్లెస్, వేల్స్ యొక్క యువరాజు","ka":"ჩარლზ მაუნტბატენ-უინძორი","lt":"Princas Čarlzas","nb":"Charles III av Storbritannia","vi":"Charles, Thân vương xứ Wales","si":"චාල්ස් කුමාරයා","ml":"ചാൾസ് രാജകുമാരൻ","sk":"Karol III.","fy":"Charles, prins fan Wales","bn":"তৃতীয় চার্লস","tl":"Charles III","tt":"Велс шаһзадәсе Чарлз","zh-hk":"查理斯三世","zh-cn":"查尔斯三世","zh-hans":"查尔斯三世","zh-hant":"查爾斯三世","zh-tw":"查爾斯三世","br":"Charles","de-ch":"Charles, Prince of Wales","en-ca":"Charles, Prince of Wales","en-gb":"Charles III","lb":"Charles III. vum Vereenegte Kinnekräich","pt-br":"Carlos III do Reino Unido","sh":"Charles","yi":"טשארלס דער דריטער","kk":"Чарльз","ur":"چارلس سوم","sm":"Sale","gom":"Prince Charles","scn":"Carlu d'Inghirterra","an":"Carlos de Galas","ast":"Carlos III del Reinu Xuníu","lmo":"Carl III del Regn Unid","azb":"چارلز-ولز شاهزاده‌سی","ha":"Charles, Yariman Wales","sq":"Charles, prins van Wales","wuu":"查尔斯三世","be-tarask":"Карл III","ku":"Charles, Mîrzayê Walesê","ary":"تشارلز التالت","mt":"Karlu III","ps":"چارلېس، د ويلز شهزاده","os":"Чарльз III","uz":"Charles III","am":"ቻርለስ፣ የዌልስ ልዑል","kcg":"Charles III, A̱gwam Muna̱pyia̱ A̱byintyok wu","vep":"Karl III","ne":"संयुक्त अधिराज्यका तृतीय चार्ल्स","hsb":"Charles III.","pap":"Carlos III","pap-aw":"Carlos III","xmf":"ჩარლზ III","ceb":"Karlos III","vec":"Carlo III","pam":"Karlus III","hil":"Karlos III","ilo":"Karlos III","cbk-zam":"Carlos III","pag":"Karlos III","bcl":"Karlos III","ms-arab":"چرل‌ز III","tum":"Charles III","sw":"Charles III wa Uingereza","ckb":"چارڵسی سێیەم","ban":"Charles III","ht":"Charles III (wa Wayòm Ini)","hak":"Charles 3-sṳ","pms":"Carl III dël Regn Unì","ie":"Charles III","frr":"Kaarl III. (Ferianigt Köningrik)","ny":"Charles III","km":"ឆាលស៍ទី ៣","mi":"Tāre te Tuatoru","fo":"Charles III kongur","io":"Charles la 3ma di Unionita Rejio","cdo":"Charles 3-sié","nan":"Charles 3-sè (Liân-ha̍p Ông-kok)","li":"Sjarel III van 't Vereinig Kuueninkriek","ky":"Чарльз III","as":"তৃতীয় চাৰ্লছ","gv":"Çhalse III y Reeriaght Unnaneysit","tn":"Charles III","tg":"Чарлзи III","sgs":"Karuolis III","arc":"ܬܫܐܪܠܣ ܬܠܝܬܝܐ","lzh":"查理三世","ia":"Carolo III","gsw":"Charles III. (Vereinigtes Königreich)","arq":"شارلز الثالث","no":"Charles III av Storbritannia"},"claims":{"P31":[{"value":"Q5","rank":"normal","qualifiers":{}}],"P18":[{"value":"Prince Charles in Aotearoa (cropped).jpg","rank":"normal","qualifiers":{"P2960":[{"time":"2021","timezone":0,"before":0,"after":0,"precision":9,"calendarmodel":"http://www.wikidata.org/entity/Q1985727"}]}}],"P21":[{"value":"Q6581097","rank":"normal","qualifiers":{}}],"P27":[{"value":"Q145","rank":"normal","qualifiers":{}}],"P1559":[{"value":{"text":"Charles III, King of the United Kingdom","language":"en"},"rank":"preferred","qualifiers":{"P7452":["Q71536244"]}},{"value":{"text":"Charles III","language":"en"},"rank":"normal","qualifiers":{}}],"P1477":[{"value":{"text":"Prince Charles Philip Arthur George Mountbatten-Windsor","language":"en"},"rank":"normal","qualifiers":{}}],"P735":[{"value":"Q2958359","rank":"normal","qualifiers":{"P1545":["1"],"P7338":["III"]}},{"value":"Q827311","rank":"normal","qualifiers":{"P1545":["2"],"P138":["Q80976"]}},{"value":"Q1778168","rank":"normal","qualifiers":{"P1545":["3"]}},{"value":"Q15921732","rank":"normal","qualifiers":{"P1545":["4"]}}],"P734":[{"value":"Q696647","rank":"normal","qualifiers":{}}],"P569":[{"value":{"time":"1948-11-14","timezone":0,"before":0,"after":0,"precision":11,"calendarmodel":"http://www.wikidata.org/entity/Q1985727"},"rank":"normal","qualifiers":{}}],"P19":[{"value":"Q42182","rank":"normal","qualifiers":{}}],"P22":[{"value":"Q80976","rank":"normal","qualifiers":{}}],"P25":[{"value":"Q9682","rank":"normal","qualifiers":{}}],"P26":[{"value":"Q9685","rank":"normal","qualifiers":{"P1545":["1"],"P580":[{"time":"1981-07-29","timezone":0,"before":0,"after":0,"precision":11,"calendarmodel":"http://www.wikidata.org/entity/Q1985727"}],"P2842":["Q173882"],"P805":["Q1094155"],"P582":[{"time":"1996-08-28","timezone":0,"before":0,"after":0,"precision":11,"calendarmodel":"http://www.wikidata.org/entity/Q1985727"}],"P1534":["Q93190"]}},{"value":"Q152239","rank":"preferred","qualifiers":{"P1545":["2"],"P580":[{"time":"2005-04-09","timezone":0,"before":0,"after":0,"precision":11,"calendarmodel":"http://www.wikidata.org/entity/Q1985727"}],"P2842":["Q8024616"],"P805":["Q3291135"],"P7452":["Q71536244"]}}],"P40":[{"value":"Q36812","rank":"normal","qualifiers":{}},{"value":"Q152316","rank":"normal","qualifiers":{}}],"P3373":[{"value":"Q151754","rank":"normal","qualifiers":{"P1039":["Q10943095"]}},{"value":"Q153330","rank":"normal","qualifiers":{"P1039":["Q10291472"]}},{"value":"Q154920","rank":"normal","qualifiers":{"P1039":["Q10291472"]}}],"P39":[{"value":"Q18952564","rank":"normal","qualifiers":{}},{"value":"Q180729","rank":"normal","qualifiers":{"P580":[{"time":"1958-07-26","timezone":0,"before":0,"after":0,"precision":11,"calendarmodel":"http://www.wikidata.org/entity/Q1985727"}],"P1365":["Q590227"],"P582":[{"time":"2022-09-08","timezone":0,"before":0,"after":0,"precision":11,"calendarmodel":"http://www.wikidata.org/entity/Q1985727"}],"P1366":["Q36812"]}},{"value":"Q28841847","rank":"normal","qualifiers":{}},{"value":"Q2762318","rank":"normal","qualifiers":{"P642":["Q9134365"],"P580":[{"time":"1948-11-14","timezone":0,"before":0,"after":0,"precision":11,"calendarmodel":"http://www.wikidata.org/entity/Q1985727"}],"P582":[{"time":"2022-09-08","timezone":0,"before":0,"after":0,"precision":11,"calendarmodel":"http://www.wikidata.org/entity/Q1985727"}],"P1366":["Q36812"]}},{"value":"Q2762318","rank":"normal","qualifiers":{"P642":["Q824569"],"P580":[{"time":"1948-11-14","timezone":0,"before":0,"after":0,"precision":11,"calendarmodel":"http://www.wikidata.org/entity/Q1985727"}],"P582":[{"time":"2021-04-09","timezone":0,"before":0,"after":0,"precision":11,"calendarmodel":"http://www.wikidata.org/entity/Q1985727"}],"P1534":["Q46992747"]}},{"value":"Q9134365","rank":"preferred","qualifiers":{"P1365":["Q9682"],"P580":[{"time":"2022-09-08","timezone":0,"before":0,"after":0,"precision":11,"calendarmodel":"http://www.wikidata.org/entity/Q1985727"}]}},{"value":"Q26869650","rank":"normal","qualifiers":{"P1366":[],"P580":[{"time":"2022-09-08","timezone":0,"before":0,"after":0,"precision":11,"calendarmodel":"http://www.wikidata.org/entity/Q1985727"}],"P1365":["Q9682"]}},{"value":"Q26869636","rank":"normal","qualifiers":{"P580":[{"time":"2022-09-08","timezone":0,"before":0,"after":0,"precision":11,"calendarmodel":"http://www.wikidata.org/entity/Q1985727"}],"P1365":["Q9682"]}},{"value":"Q34517433","rank":"normal","qualifiers":{"P1365":["Q9682"],"P580":[{"time":"2022-09-08","timezone":0,"before":0,"after":0,"precision":11,"calendarmodel":"http://www.wikidata.org/entity/Q1985727"}]}},{"value":"Q34517722","rank":"normal","qualifiers":{"P1365":["Q9682"],"P580":[{"time":"2022-09-08","timezone":0,"before":0,"after":0,"precision":11,"calendarmodel":"http://www.wikidata.org/entity/Q1985727"}]}},{"value":"Q34517851","rank":"normal","qualifiers":{"P1365":["Q9682"],"P580":[{"time":"2022-09-08","timezone":0,"before":0,"after":0,"precision":11,"calendarmodel":"http://www.wikidata.org/entity/Q1985727"}]}},{"value":"Q34518009","rank":"normal","qualifiers":{"P1365":["Q9682"],"P580":[{"time":"2022-09-08","timezone":0,"before":0,"after":0,"precision":11,"calendarmodel":"http://www.wikidata.org/entity/Q1985727"}]}},{"value":"Q34518124","rank":"normal","qualifiers":{"P580":[{"time":"2022-09-08","timezone":0,"before":0,"after":0,"precision":11,"calendarmodel":"http://www.wikidata.org/entity/Q1985727"}],"P1365":["Q9682"]}},{"value":"Q14931511","rank":"normal","qualifiers":{"P580":[{"time":"2022-09-08","timezone":0,"before":0,"after":0,"precision":11,"calendarmodel":"http://www.wikidata.org/entity/Q1985727"}]}},{"value":"Q14931512","rank":"normal","qualifiers":{"P580":[{"time":"2022-09-08","timezone":0,"before":0,"after":0,"precision":11,"calendarmodel":"http://www.wikidata.org/entity/Q1985727"}]}},{"value":"Q14931517","rank":"normal","qualifiers":{"P580":[{"time":"2022-09-08","timezone":0,"before":0,"after":0,"precision":11,"calendarmodel":"http://www.wikidata.org/entity/Q1985727"}]}},{"value":"Q26869648","rank":"normal","qualifiers":{"P580":[{"time":"2022-09-08","timezone":0,"before":0,"after":0,"precision":11,"calendarmodel":"http://www.wikidata.org/entity/Q1985727"}]}},{"value":"Q26869642","rank":"normal","qualifiers":{"P580":[{"time":"2022-09-08","timezone":0,"before":0,"after":0,"precision":11,"calendarmodel":"http://www.wikidata.org/entity/Q1985727"}]}},{"value":"Q26869646","rank":"normal","qualifiers":{"P580":[{"time":"2022-09-08","timezone":0,"before":0,"after":0,"precision":11,"calendarmodel":"http://www.wikidata.org/entity/Q1985727"}]}},{"value":"Q26869653","rank":"normal","qualifiers":{"P580":[{"time":"2022-09-08","timezone":0,"before":0,"after":0,"precision":11,"calendarmodel":"http://www.wikidata.org/entity/Q1985727"}]}},{"value":"Q280751","rank":"normal","qualifiers":{"P580":[{"time":"2022-09-08","timezone":0,"before":0,"after":0,"precision":11,"calendarmodel":"http://www.wikidata.org/entity/Q1985727"}]}},{"value":"Q460057","rank":"normal","qualifiers":{"P580":[{"time":"2022-09-08","timezone":0,"before":0,"after":0,"precision":11,"calendarmodel":"http://www.wikidata.org/entity/Q1985727"}]}},{"value":"Q116046099","rank":"normal","qualifiers":{"P580":[{"time":"1977-01-01","timezone":0,"before":0,"after":0,"precision":11,"calendarmodel":"http://www.wikidata.org/entity/Q1985727"}]}}],"P69":[{"value":"Q319761","rank":"normal","qualifiers":{"P585":[{"time":"1969-04","timezone":0,"before":0,"after":0,"precision":10,"calendarmodel":"http://www.wikidata.org/entity/Q1985727"}],"P582":[{"time":"1969-06","timezone":0,"before":0,"after":0,"precision":10,"calendarmodel":"http://www.wikidata.org/entity/Q1985727"}]}},{"value":"Q332342","rank":"normal","qualifiers":{"P580":[{"time":"1967-10","timezone":0,"before":0,"after":0,"precision":10,"calendarmodel":"http://www.wikidata.org/entity/Q1985727"}],"P582":[{"time":"1970-06-23","timezone":0,"before":0,"after":0,"precision":11,"calendarmodel":"http://www.wikidata.org/entity/Q1985727"}],"P512":["Q1765120"]}},{"value":"Q7373601","rank":"normal","qualifiers":{"P580":[{"time":"1971-03","timezone":0,"before":0,"after":0,"precision":10,"calendarmodel":"http://www.wikidata.org/entity/Q1985727"}],"P582":[{"time":"1971-09","timezone":0,"before":0,"after":0,"precision":10,"calendarmodel":"http://www.wikidata.org/entity/Q1985727"}]}},{"value":"Q14993395","rank":"normal","qualifiers":{}},{"value":"Q5088830","rank":"normal","qualifiers":{"P580":[{"time":"1957","timezone":0,"before":0,"after":0,"precision":9,"calendarmodel":"http://www.wikidata.org/entity/Q1985727"}]}},{"value":"Q1538148","rank":"normal","qualifiers":{"P580":[{"time":"1962-04","timezone":0,"before":0,"after":0,"precision":10,"calendarmodel":"http://www.wikidata.org/entity/Q1985727"}],"P582":[{"time":"1967-07","timezone":0,"before":0,"after":0,"precision":10,"calendarmodel":"http://www.wikidata.org/entity/Q1985727"}]}},{"value":"Q48814228","rank":"normal","qualifiers":{"P580":[{"time":"1966","timezone":0,"before":0,"after":0,"precision":9,"calendarmodel":"http://www.wikidata.org/entity/Q1985727"}],"P582":[{"time":"1966","timezone":0,"before":0,"after":0,"precision":9,"calendarmodel":"http://www.wikidata.org/entity/Q1985727"}]}},{"value":"Q90866585","rank":"normal","qualifiers":{"P580":[{"time":"1956-11-07","timezone":0,"before":0,"after":0,"precision":11,"calendarmodel":"http://www.wikidata.org/entity/Q1985727"}],"P582":[{"time":"1957","timezone":0,"before":0,"after":0,"precision":9,"calendarmodel":"http://www.wikidata.org/entity/Q1985727"}]}},{"value":"Q1795492","rank":"normal","qualifiers":{"P580":[{"time":"1971","timezone":0,"before":0,"after":0,"precision":9,"calendarmodel":"http://www.wikidata.org/entity/Q1985727"}]}}],"P511":[{"value":"Q669458","rank":"normal","qualifiers":{}}],"P1290":[{"value":"Q280856","rank":"normal","qualifiers":{}},{"value":"Q76927","rank":"normal","qualifiers":{}},{"value":"Q153815","rank":"normal","qualifiers":{}},{"value":"Q259488","rank":"normal","qualifiers":{}},{"value":"Q336691","rank":"normal","qualifiers":{}},{"value":"Q154927","rank":"normal","qualifiers":{"P1875":["Q335091"]}},{"value":"Q170396","rank":"normal","qualifiers":{"P1875":["Q80976"]}},{"value":"Q5231604","rank":"normal","qualifiers":{}}],"P1038":[{"value":"Q3736070","rank":"normal","qualifiers":{"P1039":["Q4346792"]}},{"value":"Q3743314","rank":"normal","qualifiers":{"P1039":["Q19822354"]}}],"P2561":[],"P1950":[],"P5056":[],"P2652":[],"P570":[],"P102":[],"P3602":[],"P3448":[],"P451":[],"P8810":[]},"sitelinks":{"afwiki":"Charles III van die Verenigde Koninkryk","alswiki":"Charles III. (Vereinigtes Königreich)","amwiki":"ሦስተኛው ቻርለስ","angwiki":"Carl III Bretta Cyning","anwiki":"Carlos III d'o Reino Uniu","arcwiki":"ܬܫܐܪܠܣ ܬܠܝܬܝܐ","arwiki":"تشارلز الثالث","arywiki":"تشارلز التالت","arzwiki":"تشارلز التالت","astwiki":"Carlos III del Reinu Xuníu","aswiki":"তৃতীয় চাৰ্লছ","azbwiki":"اوچونجو چارلز","azwiki":"III Çarlz","banwiki":"Charles III","bat_smgwiki":"Karuolis III","be_x_oldwiki":"Карл III (кароль Вялікабрытаніі)","bewiki":"Карл III (кароль Вялікабрытаніі)","bgwiki":"Чарлз III","bnwiki":"তৃতীয় চার্লস","brwiki":"Charlez III (Rouantelezh-Unanet)","bswiki":"Charles III","bswikiquote":"Charles, princ od Velsa","cawiki":"Carles III del Regne Unit","cdowiki":"Charles 3-sié","ckbwiki":"چارڵسی سێیەم","commonswiki":"Charles III of the United Kingdom","cswiki":"Karel III. Britský","cswikiquote":"Karel III. Britský","cywiki":"Siarl III, brenin y Deyrnas Unedig","dawiki":"Charles 3. af Storbritannien","dewiki":"Charles III.","elwiki":"Κάρολος Γ΄ του Ηνωμένου Βασιλείου","enwiki":"Charles III","enwikinews":"Category:King Charles III","enwikiquote":"Charles III","eowiki":"Karlo la 3-a (Britio)","eswiki":"Carlos III del Reino Unido","eswikiquote":"Carlos III del Reino Unido","etwiki":"Charles III","euwiki":"Karlos III.a Erresuma Batukoa","fawiki":"چارلز سوم","fiwiki":"Charles III","fowiki":"Charles III kongur","frrwiki":"Kaarl III. (Ferianigt Köningrik)","frwiki":"Charles III (roi du Royaume-Uni)","frwikiquote":"Charles III (roi du Royaume-Uni)","fywiki":"Charles III fan it Feriene Keninkryk","gawiki":"Séarlas III","gdwiki":"Teàrlach III","glwiki":"Carlos III do Reino Unido","gomwiki":"Prince Charles","guwiki":"પ્રિન્સ ચાર્લ્સ","gvwiki":"Çhalse III y Reeriaght Unnaneysit","hakwiki":"Charles 3-sṳ","hawiki":"Charles III","hewiki":"צ'ארלס השלישי, מלך הממלכה המאוחדת","hiwiki":"चार्ल्स तृतीय","hrwiki":"Karlo III., kralj Ujedinjenog Kraljevstva","hsbwiki":"Charles III.","htwiki":"Charles III (wa Wayòm Ini)","huwiki":"III. Károly brit király","hywiki":"Չարլզ III (Մեծ Բրիտանիայի թագավոր)","iawiki":"Carolo III del Regno Unite","idwiki":"Charles III dari Britania Raya","iewiki":"Charles III","iowiki":"Charles la 3ma di Unionita Rejio","iswiki":"Karl 3. Bretakonungur","itwiki":"Carlo III del Regno Unito","itwikiquote":"Carlo III del Regno Unito","jawiki":"チャールズ3世 (イギリス王)","kawiki":"ჩარლზ III","kcgwiki":"Charles III","kkwiki":"III Чарлз","kmwiki":"ឆាលស៍ទី ៣","kowiki":"찰스 3세","kuwiki":"Charles III","kwwiki":"Charlys III","kywiki":"Чарльз III","lawiki":"Carolus III (rex Britanniarum)","lbwiki":"Charles III. vum Vereenegte Kinnekräich","liwiki":"Sjarel III van 't Vereinig Kuueninkriek","lmowiki":"Carl III del Regn Unid","ltwiki":"Karolis III (Jungtinė Karalystė)","lvwiki":"Čārlzs III Vindzors","miwiki":"Tiāre te Tuatoru","mkwiki":"Чарлс III","mlwiki":"ചാൾസ് മൂന്നാമൻ","mnwiki":"III Чарльз","mrwiki":"युनायटेड किंग्डमचा तिसरा चार्ल्स","mswiki":"Charles III","mtwiki":"Karlu III","mywiki":"တတိယမြောက် ချားလ်စ်ဘုရင်","newiki":"चार्ल्स तृतीय","nlwiki":"Charles III van het Verenigd Koninkrijk","nnwiki":"Charles III av Storbritannia","nowiki":"Charles III av Storbritannia","nywiki":"Charles III","ocwiki":"Carles III (Reiaume Unit)","papwiki":"Carlos III","plwiki":"Karol III","plwikiquote":"Karol Mountbatten-Windsor","pmswiki":"Carl III dël Regn Unì","pnbwiki":"بادشاہ چارلس","pswiki":"چارلېس، د ويلز شهزاده","ptwiki":"Carlos III do Reino Unido","ptwikiquote":"Carlos III do Reino Unido","rowiki":"Charles al III-lea","ruwiki":"Карл III (король Великобритании)","ruwikiquote":"Карл III (король Великобритании)","scnwiki":"Carlu III dû Regnu Unitu","scowiki":"Charles III","sewiki":"Charles (Walesa prinsa)","shwiki":"Charles III od Ujedinjenog Kraljevstva","simplewiki":"Charles III","siwiki":"තෙවන චාල්ස් රජ","skwiki":"Karol III. (Spojené kráľovstvo)","slwiki":"Karel III., kralj Združenega kraljestva","smwiki":"Sale III","sqwiki":"Çarls i Uellsit","srwiki":"Чарлс III","srwikiquote":"Чарлс III","svwiki":"Charles III av Storbritannien","swwiki":"Charles III wa Uingereza","tawiki":"ஐக்கிய இராச்சியத்தின் மூன்றாம் சார்லசு","tewiki":"చార్లెస్ III","tgwiki":"Чарлзи III","thwiki":"สมเด็จพระเจ้าชาลส์ที่ 3 แห่งสหราชอาณาจักร","tlwiki":"Charles III","tnwiki":"Charles III","trwiki":"III. Charles","ttwiki":"Çarlz III (Böyekbritaniä patşası)","tumwiki":"Charles III","ukwiki":"Чарльз III","urwiki":"چارلس سوم","uzwiki":"Charles III","viwiki":"Charles III","warwiki":"Charles III","wuuwiki":"查尔斯三世","xmfwiki":"ჩარლზ III","yiwiki":"טשארלס דער דריטער","zh_min_nanwiki":"Charles 3-sè (Liân-ha̍p Ông-kok)","zh_yuewiki":"查理斯三世","zhwiki":"查爾斯三世"}}
{"id":"Q5026702","type":"item","modified":"2022-10-18T15:32:03Z","labels":{"en":"Camillo Gonsalves","nl":"Camillo Gonsalves","de":"Camillo Gonsalves","fr":"Camillo Gonsalves","it":"Camillo Gonsalves","la":"Camillus Gonsalves","zh":"龔沙福","pt-br":"Camillo Gonsalves","ast":"Camillo Gonsalves","es":"Camillo Gonsalves","ga":"Camillo Gonsalves","uk":"Камілло Гонсалвіш","sq":"Camillo Gonsalves","arz":"كاميلو جونسالڤيس","pt":"Camillo Gonsalves","ja":"カミーロ・ゴンサルヴェス","ru":"Гонсалвеш, Камилло"},"claims":{"P31":[{"value":"Q5","rank":"normal","qualifiers":{}}],"P18":[{"value":"Camillo Gonsalves.jpg","rank":"normal","qualifiers":{}},{"value":"Camillo Gonsalves 2017.jpg","rank":"preferred","qualifiers":{}}],"P21":[{"value":"Q6581097","rank":"normal","qualifiers":{}}],"P27":[{"value":"Q757","rank":"normal","qualifiers":{}}],"P735":[{"value":"Q20000570","rank":"normal","qualifiers":{}}],"P734":[{"value":"Q37433300","rank":"normal","qualifiers":{}}],"P569":[{"value":{"time":"1972-06-12","timezone":0,"before":0,"after":0,"precision":11,"calendarmodel":"http://www.wikidata.org/entity/Q1985727"},"rank":"normal","qualifiers":{}}],"P19":[{"value":"Q1345","rank":"normal","qualifiers":{}}],"P22":[{"value":"Q57800","rank":"normal","qualifiers":{}}],"P39":[{"value":"Q112609747","rank":"normal","qualifiers":{"P580":[{"time":"2020-11-10","timezone":0,"before":0,"after":0,"precision":11,"calendarmodel":"http://www.wikidata.org/entity/Q1985727"}]}}],"P69":[{"value":"Q432637","rank":"normal","qualifiers":{}},{"value":"Q49210","rank":"normal","qualifiers":{}},{"value":"Q1420239","rank":"normal","qualifiers":{}}],"P1559":[],"P1477":[],"P2561":[],"P1950":[],"P5056":[],"P2652":[],"P570":[],"P25":[],"P26":[],"P40":[],"P3373":[],"P511":[],"P102":[],"P3602":[],"P3448":[],"P451":[],"P1290":[],"P8810":[],"P1038":[]},"sitelinks":{"arzwiki":"كاميلو جونسالڤيس","commonswiki":"Category:Camillo Gonsalves","enwiki":"Camillo Gonsalves","lawiki":"Camillus Gonsalves","ruwiki":"Гонсалвеш, Камилло","ukwiki":"Камілло Гонсалвіш"}}
{"id":"Q57800","type":"item","modified":"2022-11-18T23:36:54Z","labels":{"pt":"Ralph Gonsalves","zh":"拉尔夫·冈萨维斯","pl":"Ralph Gonsalves","fr":"Ralph Gonsalves","ru":"Ральф Гонсалвеш","ast":"Ralph Gonsalves","en":"Ralph Gonsalves","es":"Ralph Gonsalves","tr":"Ralph Gonsalves","yo":"Ralph Gonsalves","fi":"Ralph Gonsalves","it":"Ralph Gonsalves","gl":"Ralph Gonsalves","et":"Ralph Gonsalves","de":"Ralph Gonsalves","id":"Ralph Gonsalves","el":"Ραλφ Γκονσάλβες","sh":"Ralph Gonsalves","nb":"Ralph Gonsalves","sv":"Ralph Gonsalves","nl":"Ralph Gonsalves","ca":"Ralph Gonsalves","oc":"Ralph Gonsalves","da":"Ralph Gonsalves","nn":"Ralph Gonsalves","fa":"رالف گونسالوس","la":"Radulphus Gonsalves","hu":"Ralph Gonsalves","ja":"ラルフ・ゴンサルベス","he":"רלף גונזלבס","sl":"Ralph Gonsalves","pt-br":"Ralph Gonsalves","uk":"Ральф Гонсалвіш","zh-hant":"龔薩福","sq":"Ralph Gonsalves","arz":"رالف جونسالڤيس","sr":"Ралф Гонсалвес","ms":"Ralph Gonsalves"},"claims":{"P31":[{"value":"Q5","rank":"normal","qualifiers":{}}],"P18":[{"value":"Ralph Gonsalves (cropped).jpg","rank":"normal","qualifiers":{}}],"P21":[{"value":"Q6581097","rank":"normal","qualifiers":{}}],"P27":[{"value":"Q757","rank":"normal","qualifiers":{}}],"P1559":[{"value":{"text":"Ralph Everard Gonsalves","language":"en"},"rank":"normal","qualifiers":{}}],"P735":[{"value":"Q18156180","rank":"normal","qualifiers":{}}],"P734":[{"value":"Q37433300","rank":"normal","qualifiers":{}}],"P569":[{"value":{"time":"1946-08-08","timezone":0,"before":0,"after":0,"precision":11,"calendarmodel":"http://www.wikidata.org/entity/Q1985727"},"rank":"normal","qualifiers":{}}],"P19":[{"value":"Q4490329","rank":"normal","qualifiers":{}}],"P40":[{"value":"Q5026702","rank":"normal","qualifiers":{}}],"P39":[{"value":"Q30101507","rank":"normal","qualifiers":{"P1545":["4"],"P580":[{"time":"2001-03-28","timezone":0,"before":0,"after":0,"precision":11,"calendarmodel":"http://www.wikidata.org/entity/Q1985727"}],"P1365":["Q1268324"]}},{"value":"Q114739225","rank":"normal","qualifiers":{"P580":[{"time":"2020-11-10","timezone":0,"before":0,"after":0,"precision":11,"calendarmodel":"http://www.wikidata.org/entity/Q1985727"}]}},{"value":"Q114739113","rank":"normal","qualifiers":{"P580":[{"time":"2020-11-10","timezone":0,"before":0,"after":0,"precision":11,"calendarmodel":"http://www.wikidata.org/entity/Q1985727"}]}},{"value":"Q114739521","rank":"normal","qualifiers":{"P580":[{"time":"2020-11-10","timezone":0,"before":0,"after":0,"precision":11,"calendarmodel":"http://www.wikidata.org/entity/Q1985727"}]}},{"value":"Q19901423","rank":"normal","qualifiers":{"P580":[{"time":"2020-11-10","timezone":0,"before":0,"after":0,"precision":11,"calendarmodel":"http://www.wikidata.org/entity/Q1985727"}],"P582":[{"time":"2022-08-16","timezone":0,"before":0,"after":0,"precision":11,"calendarmodel":"http://www.wikidata.org/entity/Q1985727"}],"P1366":["Q115263405"]}}],"P69":[{"value":"Q746153","rank":"normal","qualifiers":{}}],"P102":[{"value":"Q1277617","rank":"normal","qualifiers":{}}],"P1477":[],"P2561":[],"P1950":[],"P5056":[],"P2652":[],"P570":[],"P22":[],"P25":[],"P26":[],"P3373":[],"P511":[],"P3602":[],"P3448":[],"P451":[],"P1290":[],"P8810":[],"P1038":[]},"sitelinks":{"arzwiki":"رالف جونسالڤيس","astwiki":"Ralph Gonsalves","cawiki":"Ralph Gonsalves","commonswiki":"Category:Ralph Gonsalves","dawiki":"Ralph Gonsalves","dewiki":"Ralph Gonsalves","elwiki":"Ραλφ Γκονσάλβες","enwiki":"Ralph Gonsalves","enwikiquote":"Ralph Gonsalves","eswiki":"Ralph Gonsalves","etwiki":"Ralph Gonsalves","fawiki":"رالف گونسالوس","fiwiki":"Ralph Gonsalves","frwiki":"Ralph Gonsalves","glwiki":"Ralph Gonsalves","hewiki":"רלף גונזלבס","idwiki":"Ralph Gonsalves","itwiki":"Ralph Gonsalves","jawiki":"ラルフ・ゴンサルヴェス","lawiki":"Radulphus Gonsalves","mswiki":"Ralph Gonsalves","nowiki":"Ralph Gonsalves","plwiki":"Ralph Gonsalves","ptwiki":"Ralph Gonsalves","ruwiki":"Гонсалвеш, Ральф","shwiki":"Ralph Gonsalves","simplewiki":"Ralph Gonsalves","srwiki":"Ралф Гонсалвес","trwiki":"Ralph Gonsalves","ukwiki":"Ральф Гонсалвіш","yowiki":"Ralph Gonsalves","zhwiki":"拉尔夫·冈萨维斯"}}
{"id":"Q58248","type":"item","modified":"2022-10-18T14:46:48Z","labels":{"de":"Louis Straker","fr":"Louis Straker","en":"Louis Straker","es":"Louis Straker","ca":"Louis Straker","oc":"Louis Straker","nb":"Louis Straker","da":"Louis Straker","nn":"Louis Straker","sv":"Louis Straker","nl":"Louis Straker","la":"Ludovicus Straker","hu":"Louis Straker","ja":"ルイス・ストレーカー","sl":"Louis Straker","zh":"路易斯·斯特雷克","ast":"Louis Straker","uk":"Луїс Гілтон Штракер","sq":"Louis Straker","arz":"لويس ستراكر"},"claims":{"P31":[{"value":"Q5","rank":"normal","qualifiers":{}}],"P18":[{"value":"Louis Straker with Obamas cropped.jpg","rank":"normal","qualifiers":{}}],"P21":[{"value":"Q6581097","rank":"normal","qualifiers":{}}],"P27":[{"value":"Q757","rank":"normal","qualifiers":{}}],"P735":[{"value":"Q2897866","rank":"normal","qualifiers":{}}],"P734":[{"value":"Q7621178","rank":"normal","qualifiers":{}}],"P569":[{"value":{"time":"1944-02-23","timezone":0,"before":0,"after":0,"precision":11,"calendarmodel":"http://www.wikidata.org/entity/Q1985727"},"rank":"normal","qualifiers":{}}],"P19":[{"value":"Q2630835","rank":"normal","qualifiers":{}}],"P39":[{"value":"Q114739134","rank":"normal","qualifiers":{"P580":[{"time":"2015-12-10","timezone":0,"before":0,"after":0,"precision":11,"calendarmodel":"http://www.wikidata.org/entity/Q1985727"}],"P1365":["Q86713407"],"P582":[{"time":"2020-11-07","timezone":0,"before":0,"after":0,"precision":11,"calendarmodel":"http://www.wikidata.org/entity/Q1985727"}],"P1366":["Q101693621"]}}],"P69":[{"value":"Q762266","rank":"normal","qualifiers":{}}],"P102":[{"value":"Q1277617","rank":"normal","qualifiers":{}}],"P1559":[],"P1477":[],"P2561":[],"P1950":[],"P5056":[],"P2652":[],"P570":[],"P22":[],"P25":[],"P26":[],"P40":[],"P3373":[],"P511":[],"P3602":[],"P3448":[],"P451":[],"P1290":[],"P8810":[],"P1038":[]},"sitelinks":{"arzwiki":"لويس ستراكر","commonswiki":"Category:Louis Straker","dewiki":"Louis Straker","enwiki":"Louis Straker","frwiki":"Louis Straker","lawiki":"Ludovicus Straker","ukwiki":"Луїс Гілтон Штракер"}}
{"id":"Q66088003","type":"item","modified":"2022-10-18T14:04:46Z","labels":{"en":"Susan Dougan","nb":"Susan Dougan","ast":"Susan Dougan","nl":"Susan Dougan","uk":"Сьюзен Дуган","pl":"Susan Dougan","zh":"蘇珊·杜根","de":"Susan Dougan","fr":"Susan Dougan","tr":"Susan Dougan","ja":"スーザン・ドゥーガン","es":"Susan Dougan","fa":"سوزان دوگان","he":"סוזן דוגאן","et":"Susan Dougan","pt":"Susan Dougan","el":"Σούζαν Ντούγκαν","fi":"Susan Dougan","pt-br":"Susan Dougan","sv":"Susan Dougan","id":"Susan Dougan","ru":"Дуган, Сьюзан"},"claims":{"P31":[{"value":"Q5","rank":"normal","qualifiers":{}}],"P18":[{"value":"GG Susan Dougan (profile).jpg","rank":"normal","qualifiers":{"P585":[{"time":"2021-11-23","timezone":0,"before":0,"after":0,"precision":11,"calendarmodel":"http://www.wikidata.org/entity/Q1985727"}]}},{"value":"Susan Dougan 2019.jpg","rank":"preferred","qualifiers":{"P585":[{"time":"2019-10-08","timezone":0,"before":0,"after":0,"precision":11,"calendarmodel":"http://www.wikidata.org/entity/Q1985727"}]}}],"P21":[{"value":"Q6581072","rank":"normal","qualifiers":{}}],"P27":[{"value":"Q757","rank":"normal","qualifiers":{}}],"P735":[{"value":"Q14936243","rank":"normal","qualifiers":{}}],"P734":[{"value":"Q12787770","rank":"normal","qualifiers":{}}],"P569":[{"value":{"time":"1955-03-03","timezone":0,"before":0,"after":0,"precision":11,"calendarmodel":"http://www.wikidata.org/entity/Q1985727"},"rank":"normal","qualifiers":{}}],"P19":[{"value":"Q4490329","rank":"normal","qualifiers":{}}],"P39":[{"value":"Q61037457","rank":"normal","qualifiers":{}},{"value":"Q61037457","rank":"normal","qualifiers":{"P580":[{"time":"2019-08-01","timezone":0,"before":0,"after":0,"precision":11,"calendarmodel":"http://www.wikidata.org/entity/Q1985727"}]}}],"P1559":[],"P1477":[],"P2561":[],"P1950":[],"P5056":[],"P2652":[],"P570":[],"P22":[],"P25":[],"P26":[],"P40":[],"P3373":[],"P69":[],"P511":[],"P102":[],"P3602":[],"P3448":[],"P451":[],"P1290":[],"P8810":[],"P1038":[]},"sitelinks":{"commonswiki":"Category:Susan Dougan","dewiki":"Susan Dougan","elwiki":"Σούζαν Ντούγκαν","enwiki":"Susan Dougan","eswiki":"Susan Dougan","etwiki":"Susan Dougan","fawiki":"سوزان دوگان","fiwiki":"Susan Dougan","frwiki":"Susan Dougan","idwiki":"Susan Dougan","nowiki":"Susan Dougan","plwiki":"Susan Dougan","ptwiki":"Susan Dougan","ruwiki":"Дуган, Сьюзан","simplewiki":"Susan Dougan","svwiki":"Susan Dougan","trwiki":"Susan Dougan","ukwiki":"Сьюзен Дуган"}}
{"id":"Q6899931","type":"item","modified":"2022-10-21T17:32:42Z","labels":{"el":"Μόνικα Ντέικον","en":"Monica Dacon","es":"Monica Dacon","nl":"Monica Dacon","fr":"Monica Dacon","de":"Monica Dacon","hu":"Monica Dacon","zh-hant":"莫妮卡·達康","zh-cn":"莫妮卡·达康","ja":"モニカ・ダコン","hi":"मॉनिका डेकन","zh-hans":"莫妮卡·达康","ast":"Monica Dacon","vi":"Monica Dacon","zh":"莫妮卡·达康","fa":"مونیکا دیکن","sv":"Monica Dacon","ru":"Дейкон, Моника"},"claims":{"P31":[{"value":"Q5","rank":"normal","qualifiers":{}}],"P18":[{"value":"Dame Monica Dacon (cropped).JPG","rank":"normal","qualifiers":{"P585":[{"time":"2012-10-11","timezone":0,"before":0,"after":0,"precision":11,"calendarmodel":"http://www.wikidata.org/entity/Q1985727"}]}}],"P21":[{"value":"Q6581072","rank":"normal","qualifiers":{}}],"P27":[{"value":"Q757","rank":"normal","qualifiers":{}}],"P735":[{"value":"Q14013933","rank":"normal","qualifiers":{}}],"P734":[{"value":"Q37438809","rank":"normal","qualifiers":{}}],"P569":[{"value":{"time":"1934-06-04","timezone":0,"before":0,"after":0,"precision":11,"calendarmodel":"http://www.wikidata.org/entity/Q1985727"},"rank":"normal","qualifiers":{}}],"P19":[{"value":"Q2660774","rank":"normal","qualifiers":{}}],"P39":[{"value":"Q61037457","rank":"normal","qualifiers":{"P580":[{"time":"2002-06-03","timezone":0,"before":0,"after":0,"precision":11,"calendarmodel":"http://www.wikidata.org/entity/Q1985727"}],"P582":[{"time":"2002-09-02","timezone":0,"before":0,"after":0,"precision":11,"calendarmodel":"http://www.wikidata.org/entity/Q1985727"}],"P1365":["Q3560964"],"P1366":["Q354705"]}}],"P69":[{"value":"Q746153","rank":"normal","qualifiers":{}}],"P1559":[],"P1477":[],"P2561":[],"P1950":[],"P5056":[],"P2652":[],"P570":[],"P22":[],"P25":[],"P26":[],"P40":[],"P3373":[],"P511":[],"P102":[],"P3602":[],"P3448":[],"P451":[],"P1290":[],"P8810":[],"P1038":[]},"sitelinks":{"dewiki":"Monica Dacon","elwiki":"Μόνικα Ντέικον","enwiki":"Monica Dacon","fawiki":"مونیکا دیکن","frwiki":"Monica Dacon","hiwiki":"मॉनिका डेकन","ruwiki":"Дейкон, Моника","simplewiki":"Monica Dacon","svwiki":"Monica Dacon","viwiki":"Monica Dacon"}}
{"id":"Q86713407","type":"item","modified":"2023-01-07T17:16:51Z","labels":{"fr":"Girlyn Miguel","nl":"Girlyn Miguel","en":"Girlyn Miguel","ast":"Girlyn Miguel","zh":"格尔琳·米盖尔"},"claims":{"P31":[{"value":"Q5","rank":"normal","qualifiers":{}}],"P18":[{"value":"Hon. Girlyn Miguel (cropped).jpg","rank":"normal","qualifiers":{"P585":[{"time":"2013","timezone":0,"before":0,"after":0,"precision":9,"calendarmodel":"http://www.wikidata.org/entity/Q1985727"}]}}],"P21":[{"value":"Q6581072","rank":"normal","qualifiers":{}}],"P27":[{"value":"Q757","rank":"normal","qualifiers":{}}],"P569":[{"value":{"time":"1948","timezone":0,"before":0,"after":0,"precision":9,"calendarmodel":"http://www.wikidata.org/entity/Q1985727"},"rank":"normal","qualifiers":{}}],"P39":[{"value":"Q86713609","rank":"normal","qualifiers":{"P580":[{"time":"2001-03-31","timezone":0,"before":0,"after":0,"precision":11,"calendarmodel":"http://www.wikidata.org/entity/Q1985727"}],"P582":[{"time":"2005-05-17","timezone":0,"before":0,"after":0,"precision":11,"calendarmodel":"http://www.wikidata.org/entity/Q1985727"}]}},{"value":"Q1055894","rank":"normal","qualifiers":{"P580":[{"time":"2001-03-28","timezone":0,"before":0,"after":0,"precision":11,"calendarmodel":"http://www.wikidata.org/entity/Q1985727"}],"P582":[{"time":"2005-12-07","timezone":0,"before":0,"after":0,"precision":11,"calendarmodel":"http://www.wikidata.org/entity/Q1985727"}]}},{"value":"Q1055894","rank":"normal","qualifiers":{"P580":[{"time":"2010-12-13","timezone":0,"before":0,"after":0,"precision":11,"calendarmodel":"http://www.wikidata.org/entity/Q1985727"}],"P582":[{"time":"2015-12-09","timezone":0,"before":0,"after":0,"precision":11,"calendarmodel":"http://www.wikidata.org/entity/Q1985727"}]}},{"value":"Q1055894","rank":"normal","qualifiers":{"P580":[{"time":"2005-12-07","timezone":0,"before":0,"after":0,"precision":11,"calendarmodel":"http://www.wikidata.org/entity/Q1985727"}],"P582":[{"time":"2010-12-13","timezone":0,"before":0,"after":0,"precision":11,"calendarmodel":"http://www.wikidata.org/entity/Q1985727"}]}},{"value":"Q1055894","rank":"normal","qualifiers":{"P580":[{"time":"1998-06-15","timezone":0,"before":0,"after":0,"precision":11,"calendarmodel":"http://www.wikidata.org/entity/Q1985727"}],"P582":[{"time":"2001-03-28","timezone":0,"before":0,"after":0,"precision":11,"calendarmodel":"http://www.wikidata.org/entity/Q1985727"}]}},{"value":"Q114739134","rank":"normal","qualifiers":{"P580":[{"time":"2010-12-14","timezone":0,"before":0,"after":0,"precision":11,"calendarmodel":"http://www.wikidata.org/entity/Q1985727"}],"P1365":["Q58248"],"P582":[{"time":"2015-12-09","timezone":0,"before":0,"after":0,"precision":11,"calendarmodel":"http://www.wikidata.org/entity/Q1985727"}],"P1366":["Q58248"]}}],"P1559":[],"P1477":[],"P2561":[],"P735":[],"P734":[],"P1950":[],"P5056":[],"P2652":[],"P19":[],"P570":[],"P22":[],"P25":[],"P26":[],"P40":[],"P3373":[],"P69":[],"P511":[],"P102":[],"P3602":[],"P3448":[],"P451":[],"P1290":[],"P8810":[],"P1038":[]},"sitelinks":{"enwiki":"Girlyn Miguel","frwiki":"Girlyn Miguel"}}
{"id":"Q9682","type":"item","modified":"2023-01-02T12:46:19Z","labels":{"en":"Elizabeth II","en-gb":"Elizabeth II","fr":"Élisabeth II","be-tarask":"Лізавета II","sv":"Elizabeth II","en-ca":"Elizabeth II","af":"Elizabeth II van die Verenigde Koninkryk","an":"Isabel II d'o Reino Unito","ang":"Elisabeþ II","ar":"إليزابيث الثانية","arz":"اليزابيث التانيه","ast":"Sabela II del Reinu Xuníu","az":"II Elizabet","be":"Лізавета II","bg":"Елизабет II","bi":"Elisabet II","bjn":"Elizabeth II matan Britania Raya","bn":"দ্বিতীয় এলিজাবেথ","br":"Elesbed II","bs":"Elizabeta II","ca":"Elisabet II del Regne Unit","cbk-zam":"Reina Elizabeth, el aca-segundo","ceb":"Elizabeth II sa Hiniusang Gingharian","cs":"Alžběta II.","cy":"Elisabeth II","da":"Elizabeth 2. af Storbritannien","de":"Elisabeth II.","de-ch":"Elisabeth II.","diq":"Elizabeth II","el":"Ελισάβετ Β΄ του Ηνωμένου Βασιλείου","eo":"Elizabeto la 2-a","es":"Isabel II del Reino Unido","et":"Elizabeth II","eu":"Elizabeth II.a Erresuma Batukoa","ext":"Isabel II del Réinu Uniu","fa":"الیزابت دوم","fi":"Elisabet II","frr":"Elisabeth II.","fy":"Elizabeth II fan it Feriene Keninkryk","ga":"Eilís II","gd":"Bànrigh Ealasaid II","gl":"Isabel II do Reino Unido","gv":"Ealisaid II y Reeriaght Unnaneysit","hak":"Elizabeth Ngi-sṳ","he":"אליזבת השנייה","hi":"एलिज़ाबेथ द्वितीय","hr":"Elizabeta II.","hsb":"Hilžbjeta II.","hu":"II. Erzsébet","hy":"Եղիսաբեթ II","id":"Elizabeth II dari Britania Raya","ie":"Elisabeth II","ilo":"Isabel II","io":"Elizabeth 2ma","is":"Elísabet 2. Bretadrottning","it":"Elisabetta II del Regno Unito","ja":"エリザベス2世","jv":"Elizabeth II saking Britania Raya","ka":"ელისაბედ II","kab":"Elizabeth II","kk":"Елизабет Александра Мария","kn":"ಎರಡನೇ ಎಲಿಜಬೆಥ್","ko":"엘리자베스 2세","kw":"Elisabeth II","la":"Elizabeth II","lt":"Elžbieta II","lv":"Elizabete II Vindzora","mi":"Irihapeti te Tuarua","mk":"Елизабета II","ml":"എലിസബത്ത് II","mn":"II Элизабет","mr":"एलिझाबेथ दुसरी","ms":"Elizabeth II","my":"အဲလိဇဘတ်","nah":"Cihuātlahtoāni Elizabeth II","nl":"Elizabeth II van het Verenigd Koninkrijk","nn":"Elizabeth II av Storbritannia","nov":"Elisabeth II","nrm":"Lîzabé II du Rouoyaume Unni","nv":"Kwį́į́n Elizabeth II","oc":"Elisabeta II del Reialme Unit","os":"Елизаветæ II","pap":"Elizabeth II","pcd":"HM Queen Elizabeth II","pl":"Elżbieta II","pms":"Elisabeta II dël Regn Unì","pnb":"ملکہ الزبتھ II","pt":"Isabel II do Reino Unido","pt-br":"Elizabeth II","qu":"Elisabeth II","ro":"Elisabeta a II-a","roa-tara":"Lesabbètte II d'u Regne Aunìte","ru":"Елизавета II","sa":"एलिज़बेथ २","scn":"Elisabetta II dû Regnu Unitu","sco":"Elizabeth II","se":"Elizabeth II","sh":"Elizabeta II","si":"දෙවන එලිසබෙත් රැජින","sk":"Alžbeta II.","sl":"Elizabeta II. Britanska","so":"Elizabeth II","sq":"Elizabeth II","sr":"Елизабета II","ss":"Indlovukazi Elizabeth II","sw":"Elizabeth II wa Uingereza","ta":"ஐக்கிய இராச்சியத்தின் இரண்டாம் எலிசபெத்","te":"ఎలిజబెత్ II","th":"สมเด็จพระราชินีนาถเอลิซาเบธที่ 2 แห่งสหราชอาณาจักร","tl":"Elizabeth II","tpi":"Elisabet II","tr":"II. Elizabeth","tt":"Елизавета II","ug":"ئېلىزابېت II","uk":"Єлизавета II","ur":"ایلزبتھ دؤم","vep":"Elizavet Toine","vi":"Elizabeth II","war":"Elizabeth II han Reino Unido","yi":"עליזאבעט די צווייטע","yo":"Elisabeti Kejì","zh":"伊丽莎白二世","yue":"伊利沙伯二世","zu":"Elizabeth II","nb":"Elizabeth II","zh-hans":"伊丽莎白二世","ace":"Elizabeth II","min":"Ratu Elizabeth II","pag":"Elizabeth II","new":"संयुक्त अधिराज्ययाम्ह एलिजाबेथ निम्ह","zh-hant":"伊丽莎白二世","mt":"Reġina Eliżabetta II","am":"ንግሥት ኤልሣቤጥ","gsw":"Elisabeth II.","ckb":"ئێلیزابێتی دووەم","fur":"Regjine Bete II","lo":"ສົມເດັດພະລາຊິນີນາດເອລີຊາແບັດທີ 2 ແຫ່ງສະຫະລາຊະອານາຈັກ","pih":"Queen Elizabeth II","mg":"Elizabeth II","zh-hk":"伊利沙伯二世","zh-cn":"伊丽莎白二世","crh-latn":"II Elizabet","sgs":"Elžbieta II","nan":"Elizabeth 2-sè","zh-tw":"伊莉莎白二世","ba":"Елизавета II","brh":"Aelizbat II","ne":"एलिजाबेथ दोश्रो","ht":"Elizabeth II","cdo":"Elizabeth 2-sié","lb":"Elizabeth II.","bcl":"Reyna Elizabeth II","lmo":"Elisabetta II","xmf":"ელისაბედ II","nds":"Elisabeth II.","lrc":"ئلیزابئت دویوم","ce":"Элизабет II","sm":"Masiofo Elisapeta II","uz":"Yelizaveta II","ky":"Елизавета II","mai":"एलिजाबेथ द्वितीय","bho":"एलिजाबेथ II","azb":"ایکینجی الیزابت","gom":"Queen Elizabeth II","li":"Elizabeth II","bxr":"II Елизавета","din":"Elidhabeth II","lad":"Elizabeth II","gn":"Isabel II Tavetã Joaju pegua","wuu":"伊丽莎白二世","szl":"Elizabeth II","crh":"II Elizabet","pa":"ਐਲਿਜ਼ਾਬੈਥ II","ku":"Elizabeth II","kbp":"Elizabeth 2","vo":"Elizabeth II","ha":"Elizabeth II","fo":"Elisabeth II drotning","ps":"دوهمه ملکه الیزابت","ban":"Elizabeth II","lfn":"Elizabeth 2","szy":"Elizabeth II","tg":"Элизобети II","frp":"Èlisabèt II","ia":"Elisabeth II del Regno Unite","nqo":"ߋߟߌߖ߭ߊߓߍߕ ߂߲","hyw":"Էլիզապէթ Բ.","ary":"إيليزابيط التانية","sd":"ايلزبٿ ٻين (برطانيا)","cv":"Елизавета II","vec":"Elisabeta II del Regno Unio","haw":"Élisabeth II","ms-arab":"ايليزبث II","smn":"Elizabeth II","tay":"Elizabeth II","km":"សម្តេចព្រះរាជិនីនាថអេលីហ្សាបិតទី ២ នៃសហរាជអាណាចក្រ","ami":"Elizabeth II","trv":"Elizabeth II","de-at":"Elizabeth II","jut":"Elizabeth II","sc":"Elizabeth II","sje":"Elizabeth II","sms":"Elizabeth II","na":"Elizabeth II","arc":"ܐܠܝܙܒܬ ܬܪܝܢܝܬܐ","zea":"Elizabeth II","ny":"Elizabeth II","co":"Elizabeth II","kcg":"A̱li̱za̱ba̱t II","gpe":"Elizabeth II","shn":"ဢႄးလိၸ်ႉၸပႅတ်ႉ ထူၼ်ႈသွင်","mnw":"ဨလဳသဗေတ် ဒုတိယ","blk":"ဒုတိယ အဲလီသဘဲတ်","tum":"Elizabeth II","mni":"ꯑꯦꯂꯤꯖꯥꯕꯦꯊ ꯲","lzh":"伊莉莎白二世","dag":"Elizabeth II","av":"Элизабет II","vro":"Kuningaimänd Elizabeth II","tk":"Elizabeth II","ku-latn":"Elizabeth II","tn":"Elizabeth II","mos":"Elizabeth II","ig":"Elizabeth II","za":"Yihlisahbwz Ngeih Seiq","nap":"Elisabetta II d''o Regno Aunito","to":"ʻElisapesi II"},"claims":{"P31":[{"value":"Q5","rank":"normal","qualifiers":{}}],"P18":[{"value":"Queen Elizabeth II in March 2015.jpg","rank":"normal","qualifiers":{"P2096":[{"text":"Elizabeth II in March 2015","language":"en"},{"text":"Élisabeth II en Mars 2015","language":"fr"}],"P585":[{"time":"2015-03","timezone":0,"before":0,"after":0,"precision":10,"calendarmodel":"http://www.wikidata.org/entity/Q1985727"}]}},{"value":"Queen Elizabeth II official portrait for 1959 tour (retouched) (cropped) (3-to-4 aspect ratio).jpg","rank":"preferred","qualifiers":{"P2096":[{"text":"Elizabeth II in 1959","language":"en"},{"text":"Élisabeth II en 1959","language":"fr"},{"text":"Offisielt portrett, 1959","language":"nb"}],"P585":[{"time":"1959","timezone":0,"before":0,"after":0,"precision":9,"calendarmodel":"http://www.wikidata.org/entity/Q1985727"}]}}],"P21":[{"value":"Q6581072","rank":"normal","qualifiers":{}}],"P27":[{"value":"Q145","rank":"normal","qualifiers":{}}],"P1559":[{"value":{"text":"Elizabeth II","language":"en"},"rank":"normal","qualifiers":{}}],"P1477":[{"value":{"text":"Elizabeth Alexandra Mary Windsor","language":"en"},"rank":"normal","qualifiers":{}}],"P735":[{"value":"Q385468","rank":"preferred","qualifiers":{"P1545":["1"],"P7338":["II"],"P138":["Q10633"]}},{"value":"Q6081128","rank":"normal","qualifiers":{"P1545":["2"],"P138":["Q152260"]}},{"value":"Q734578","rank":"normal","qualifiers":{"P1545":["3"],"P138":["Q76927"]}}],"P734":[{"value":"Q27235787","rank":"normal","qualifiers":{}}],"P569":[{"value":{"time":"1926-04-21","timezone":0,"before":0,"after":0,"precision":11,"calendarmodel":"http://www.wikidata.org/entity/Q1985727"},"rank":"normal","qualifiers":{"P4241":["Q55525743"],"P421":["Q6574"]}}],"P19":[{"value":"Q124184","rank":"normal","qualifiers":{"P6375":[{"text":"17 Bruton Street","language":"en"}]}}],"P570":[{"value":{"time":"2022-09-08","timezone":0,"before":0,"after":0,"precision":11,"calendarmodel":"http://www.wikidata.org/entity/Q1985727"},"rank":"normal","qualifiers":{"P805":["Q113846055"],"P4241":["Q55811721"],"P421":["Q6655"]}}],"P22":[{"value":"Q280856","rank":"normal","qualifiers":{}}],"P25":[{"value":"Q10633","rank":"normal","qualifiers":{}}],"P26":[{"value":"Q80976","rank":"normal","qualifiers":{"P580":[{"time":"1947-11-20","timezone":0,"before":0,"after":0,"precision":11,"calendarmodel":"http://www.wikidata.org/entity/Q1985727"}],"P2842":["Q5933"],"P805":["Q7979114"],"P582":[{"time":"2021-04-09","timezone":0,"before":0,"after":0,"precision":11,"calendarmodel":"http://www.wikidata.org/entity/Q1985727"}],"P1534":["Q24037741"]}}],"P40":[{"value":"Q43274","rank":"normal","qualifiers":{}},{"value":"Q151754","rank":"normal","qualifiers":{}},{"value":"Q153330","rank":"normal","qualifiers":{}},{"value":"Q154920","rank":"normal","qualifiers":{}}],"P3373":[{"value":"Q153815","rank":"normal","qualifiers":{"P1039":["Q10943095"]}}],"P39":[{"value":"Q3052674","rank":"normal","qualifiers":{"P580":[{"time":"1952-02-06","timezone":0,"before":0,"after":0,"precision":11,"calendarmodel":"http://www.wikidata.org/entity/Q1985727"}],"P582":[{"time":"2022-09-08","timezone":0,"before":0,"after":0,"precision":11,"calendarmodel":"http://www.wikidata.org/entity/Q1985727"}]}},{"value":"Q460057","rank":"normal","qualifiers":{"P580":[{"time":"1952-02-06","timezone":0,"before":0,"after":0,"precision":11,"calendarmodel":"http://www.wikidata.org/entity/Q1985727"}],"P582":[{"time":"2022-09-08","timezone":0,"before":0,"after":0,"precision":11,"calendarmodel":"http://www.wikidata.org/entity/Q1985727"}],"P1366":["Q43274"]}},{"value":"Q34518803","rank":"normal","qualifiers":{"P1001":["Q2670092"],"P580":[{"time":"1952-02-06","timezone":0,"before":0,"after":0,"precision":11,"calendarmodel":"http://www.wikidata.org/entity/Q1985727"}],"P582":[{"time":"1972","timezone":0,"before":0,"after":0,"precision":9,"calendarmodel":"http://www.wikidata.org/entity/Q1985727"}],"P1365":["Q280856"],"P1366":[]}},{"value":"Q34518933","rank":"normal","qualifiers":{"P1001":["Q2006542"],"P580":[{"time":"1952-02-06","timezone":0,"before":0,"after":0,"precision":11,"calendarmodel":"http://www.wikidata.org/entity/Q1985727"}],"P582":[{"time":"1956","timezone":0,"before":0,"after":0,"precision":9,"calendarmodel":"http://www.wikidata.org/entity/Q1985727"}],"P1365":["Q280856"],"P1366":[]}},{"value":"Q34519042","rank":"normal","qualifiers":{"P1001":["Q193619"],"P580":[{"time":"1952-02-06","timezone":0,"before":0,"after":0,"precision":11,"calendarmodel":"http://www.wikidata.org/entity/Q1985727"}],"P582":[{"time":"1961","timezone":0,"before":0,"after":0,"precision":9,"calendarmodel":"http://www.wikidata.org/entity/Q1985727"}],"P1365":["Q280856"],"P1366":[]}},{"value":"Q34519159","rank":"normal","qualifiers":{"P1001":["Q5555325"],"P580":[{"time":"1957","timezone":0,"before":0,"after":0,"precision":9,"calendarmodel":"http://www.wikidata.org/entity/Q1985727"}],"P582":[{"time":"1960","timezone":0,"before":0,"after":0,"precision":9,"calendarmodel":"http://www.wikidata.org/entity/Q1985727"}],"P1365":[],"P1366":[]}},{"value":"Q34519272","rank":"normal","qualifiers":{"P1001":["Q5440850"],"P580":[{"time":"1960","timezone":0,"before":0,"after":0,"precision":9,"calendarmodel":"http://www.wikidata.org/entity/Q1985727"}],"P582":[{"time":"1963","timezone":0,"before":0,"after":0,"precision":9,"calendarmodel":"http://www.wikidata.org/entity/Q1985727"}],"P1365":[],"P1366":[]}},{"value":"Q34519445","rank":"normal","qualifiers":{"P1001":["Q14920623"],"P580":[{"time":"1961","timezone":0,"before":0,"after":0,"precision":9,"calendarmodel":"http://www.wikidata.org/entity/Q1985727"}],"P582":[{"time":"1971","timezone":0,"before":0,"after":0,"precision":9,"calendarmodel":"http://www.wikidata.org/entity/Q1985727"}],"P1365":[],"P1366":[]}},{"value":"Q34519551","rank":"normal","qualifiers":{"P1001":["Q7842409"],"P580":[{"time":"1962","timezone":0,"before":0,"after":0,"precision":9,"calendarmodel":"http://www.wikidata.org/entity/Q1985727"}],"P582":[{"time":"1976","timezone":0,"before":0,"after":0,"precision":9,"calendarmodel":"http://www.wikidata.org/entity/Q1985727"}],"P1365":[],"P1366":[]}},{"value":"Q34519676","rank":"normal","qualifiers":{"P1001":["Q7877575"],"P580":[{"time":"1962","timezone":0,"before":0,"after":0,"precision":9,"calendarmodel":"http://www.wikidata.org/entity/Q1985727"}],"P582":[{"time":"1963","timezone":0,"before":0,"after":0,"precision":9,"calendarmodel":"http://www.wikidata.org/entity/Q1985727"}],"P1365":[],"P1366":[]}},{"value":"Q34519772","rank":"normal","qualifiers":{"P1001":["Q6392538"],"P580":[{"time":"1963","timezone":0,"before":0,"after":0,"precision":9,"calendarmodel":"http://www.wikidata.org/entity/Q1985727"}],"P582":[{"time":"1964","timezone":0,"before":0,"after":0,"precision":9,"calendarmodel":"http://www.wikidata.org/entity/Q1985727"}],"P1365":[],"P1366":[]}},{"value":"Q34519859","rank":"normal","qualifiers":{"P1001":["Q7603765"],"P580":[{"time":"1964","timezone":0,"before":0,"after":0,"precision":9,"calendarmodel":"http://www.wikidata.org/entity/Q1985727"}],"P582":[{"time":"1974","timezone":0,"before":0,"after":0,"precision":9,"calendarmodel":"http://www.wikidata.org/entity/Q1985727"}],"P1365":[],"P1366":[]}},{"value":"Q34519933","rank":"normal","qualifiers":{"P1001":["Q7735661"],"P580":[{"time":"1965","timezone":0,"before":0,"after":0,"precision":9,"calendarmodel":"http://www.wikidata.org/entity/Q1985727"}],"P582":[{"time":"1970","timezone":0,"before":0,"after":0,"precision":9,"calendarmodel":"http://www.wikidata.org/entity/Q1985727"}],"P1365":[],"P1366":[]}},{"value":"Q34520011","rank":"normal","qualifiers":{"P1001":["Q5622720"],"P580":[{"time":"1966","timezone":0,"before":0,"after":0,"precision":9,"calendarmodel":"http://www.wikidata.org/entity/Q1985727"}],"P582":[{"time":"1970","timezone":0,"before":0,"after":0,"precision":9,"calendarmodel":"http://www.wikidata.org/entity/Q1985727"}],"P1365":[],"P1366":[]}},{"value":"Q34518634","rank":"normal","qualifiers":{"P1001":["Q14759030"],"P580":[{"time":"1968-03-12","timezone":0,"before":0,"after":0,"precision":11,"calendarmodel":"http://www.wikidata.org/entity/Q1985727"}],"P582":[{"time":"1992-03-12","timezone":0,"before":0,"after":0,"precision":11,"calendarmodel":"http://www.wikidata.org/entity/Q1985727"}],"P1365":[],"P1366":[]}},{"value":"Q34518480","rank":"normal","qualifiers":{"P1001":["Q5291089"],"P580":[{"time":"1970","timezone":0,"before":0,"after":0,"precision":9,"calendarmodel":"http://www.wikidata.org/entity/Q1985727"}],"P582":[{"time":"1987-10-06","timezone":0,"before":0,"after":0,"precision":11,"calendarmodel":"http://www.wikidata.org/entity/Q1985727"}],"P1365":[],"P1366":[]}},{"value":"Q26869644","rank":"normal","qualifiers":{"P1001":["Q244"],"P580":[{"time":"1966-11-30","timezone":0,"before":0,"after":0,"precision":11,"calendarmodel":"http://www.wikidata.org/entity/Q1985727"}],"P1365":[],"P582":[{"time":"2021-11-29","timezone":0,"before":0,"after":0,"precision":11,"calendarmodel":"http://www.wikidata.org/entity/Q1985727"}]}},{"value":"Q26869648","rank":"normal","qualifiers":{"P1001":["Q766"],"P580":[{"time":"1962-08-06","timezone":0,"before":0,"after":0,"precision":11,"calendarmodel":"http://www.wikidata.org/entity/Q1985727"}],"P1365":[],"P1366":["Q43274"],"P582":[{"time":"2022-09-08","timezone":0,"before":0,"after":0,"precision":11,"calendarmodel":"http://www.wikidata.org/entity/Q1985727"}]}},{"value":"Q26869642","rank":"normal","qualifiers":{"P1001":["Q778"],"P580":[{"time":"1973-07-10","timezone":0,"before":0,"after":0,"precision":11,"calendarmodel":"http://www.wikidata.org/entity/Q1985727"}],"P1365":[],"P1366":["Q43274"],"P582":[{"time":"2022-09-08","timezone":0,"before":0,"after":0,"precision":11,"calendarmodel":"http://www.wikidata.org/entity/Q1985727"}]}},{"value":"Q26869646","rank":"normal","qualifiers":{"P1001":["Q769"],"P580":[{"time":"1974-02-07","timezone":0,"before":0,"after":0,"precision":11,"calendarmodel":"http://www.wikidata.org/entity/Q1985727"}],"P1365":[],"P1366":["Q43274"],"P582":[{"time":"2022-09-08","timezone":0,"before":0,"after":0,"precision":11,"calendarmodel":"http://www.wikidata.org/entity/Q1985727"}]}},{"value":"Q34518124","rank":"normal","qualifiers":{"P1001":["Q691"],"P580":[{"time":"1975-09-16","timezone":0,"before":0,"after":0,"precision":11,"calendarmodel":"http://www.wikidata.org/entity/Q1985727"}],"P1365":[],"P1366":["Q43274"],"P582":[{"time":"2022-09-08","timezone":0,"before":0,"after":0,"precision":11,"calendarmodel":"http://www.wikidata.org/entity/Q1985727"}]}},{"value":"Q34518009","rank":"normal","qualifiers":{"P1001":["Q685"],"P580":[{"time":"1978-07-07","timezone":0,"before":0,"after":0,"precision":11,"calendarmodel":"http://www.wikidata.org/entity/Q1985727"}],"P1365":[],"P1366":["Q43274"],"P582":[{"time":"2022-09-08","timezone":0,"before":0,"after":0,"precision":11,"calendarmodel":"http://www.wikidata.org/entity/Q1985727"}]}},{"value":"Q34517851","rank":"normal","qualifiers":{"P1001":["Q672"],"P580":[{"time":"1978-10-01","timezone":0,"before":0,"after":0,"precision":11,"calendarmodel":"http://www.wikidata.org/entity/Q1985727"}],"P1365":[],"P1366":["Q43274"],"P582":[{"time":"2022-09-08","timezone":0,"before":0,"after":0,"precision":11,"calendarmodel":"http://www.wikidata.org/entity/Q1985727"}]}},{"value":"Q34517722","rank":"normal","qualifiers":{"P1001":["Q760"],"P580":[{"time":"1979-02-22","timezone":0,"before":0,"after":0,"precision":11,"calendarmodel":"http://www.wikidata.org/entity/Q1985727"}],"P1365":[],"P1366":["Q43274"],"P582":[{"time":"2022-09-08","timezone":0,"before":0,"after":0,"precision":11,"calendarmodel":"http://www.wikidata.org/entity/Q1985727"}]}},{"value":"Q26869653","rank":"normal","qualifiers":{"P1001":["Q757"],"P580":[{"time":"1979-10-27","timezone":0,"before":0,"after":0,"precision":11,"calendarmodel":"http://www.wikidata.org/entity/Q1985727"}],"P1365":[],"P1366":["Q43274"],"P582":[{"time":"2022-09-08","timezone":0,"before":0,"after":0,"precision":11,"calendarmodel":"http://www.wikidata.org/entity/Q1985727"}]}},{"value":"Q34517433","rank":"normal","qualifiers":{"P1001":["Q242"],"P580":[{"time":"1981-09-21","timezone":0,"before":0,"after":0,"precision":11,"calendarmodel":"http://www.wikidata.org/entity/Q1985727"}],"P1365":[],"P1366":["Q43274"],"P582":[{"time":"2022-09-08","timezone":0,"before":0,"after":0,"precision":11,"calendarmodel":"http://www.wikidata.org/entity/Q1985727"}]}},{"value":"Q26869636","rank":"normal","qualifiers":{"P1001":["Q781"],"P580":[{"time":"1981-11-01","timezone":0,"before":0,"after":0,"precision":11,"calendarmodel":"http://www.wikidata.org/entity/Q1985727"}],"P1365":[],"P1366":["Q43274"],"P582":[{"time":"2022-09-08","timezone":0,"before":0,"after":0,"precision":11,"calendarmodel":"http://www.wikidata.org/entity/Q1985727"}]}},{"value":"Q26869650","rank":"normal","qualifiers":{"P1001":["Q763"],"P580":[{"time":"1983-09-19","timezone":0,"before":0,"after":0,"precision":11,"calendarmodel":"http://www.wikidata.org/entity/Q1985727"}],"P1365":[],"P1366":["Q43274"],"P582":[{"time":"2022-09-08","timezone":0,"before":0,"after":0,"precision":11,"calendarmodel":"http://www.wikidata.org/entity/Q1985727"}]}},{"value":"Q14931517","rank":"normal","qualifiers":{"P580":[{"time":"1952-02-06","timezone":0,"before":0,"after":0,"precision":11,"calendarmodel":"http://www.wikidata.org/entity/Q1985727"}],"P1365":["Q280856"],"P1393":["Q455690"],"P1366":["Q43274"],"P582":[{"time":"2022-09-08","timezone":0,"before":0,"after":0,"precision":11,"calendarmodel":"http://www.wikidata.org/entity/Q1985727"}]}},{"value":"Q34517018","rank":"normal","qualifiers":{"P1001":["Q431731"],"P580":[{"time":"1961","timezone":0,"before":0,"after":0,"precision":9,"calendarmodel":"http://www.wikidata.org/entity/Q1985727"}],"P582":[{"time":"1962","timezone":0,"before":0,"after":0,"precision":9,"calendarmodel":"http://www.wikidata.org/entity/Q1985727"}],"P1365":[],"P1366":[]}},{"value":"Q9134365","rank":"preferred","qualifiers":{"P580":[{"time":"1952-02-06","timezone":0,"before":0,"after":0,"precision":11,"calendarmodel":"http://www.wikidata.org/entity/Q1985727"}],"P1365":["Q280856"],"P1366":["Q43274"],"P582":[{"time":"2022-09-08","timezone":0,"before":0,"after":0,"precision":11,"calendarmodel":"http://www.wikidata.org/entity/Q1985727"}]}},{"value":"Q34516586","rank":"normal","qualifiers":{"P1001":["Q6741448"],"P580":[{"time":"1964","timezone":0,"before":0,"after":0,"precision":9,"calendarmodel":"http://www.wikidata.org/entity/Q1985727"}],"P582":[{"time":"1966","timezone":0,"before":0,"after":0,"precision":9,"calendarmodel":"http://www.wikidata.org/entity/Q1985727"}],"P1365":[],"P1366":[]}},{"value":"Q14931512","rank":"normal","qualifiers":{"P580":[{"time":"1952-02-06","timezone":0,"before":0,"after":0,"precision":11,"calendarmodel":"http://www.wikidata.org/entity/Q1985727"}],"P1365":["Q280856"],"P1393":["Q610669"],"P1366":["Q43274"],"P582":[{"time":"2022-09-08","timezone":0,"before":0,"after":0,"precision":11,"calendarmodel":"http://www.wikidata.org/entity/Q1985727"}]}},{"value":"Q14931511","rank":"normal","qualifiers":{"P580":[{"time":"1952-02-06","timezone":0,"before":0,"after":0,"precision":11,"calendarmodel":"http://www.wikidata.org/entity/Q1985727"}],"P1365":["Q280856"],"P1393":["Q390776","Q1970061"],"P1366":["Q43274"],"P582":[{"time":"2022-09-08","timezone":0,"before":0,"after":0,"precision":11,"calendarmodel":"http://www.wikidata.org/entity/Q1985727"}]}},{"value":"Q280751","rank":"normal","qualifiers":{"P1393":["Q1790061"],"P580":[{"time":"1952-02-06","timezone":0,"before":0,"after":0,"precision":11,"calendarmodel":"http://www.wikidata.org/entity/Q1985727"}],"P1366":["Q43274"],"P582":[{"time":"2022-09-08","timezone":0,"before":0,"after":0,"precision":11,"calendarmodel":"http://www.wikidata.org/entity/Q1985727"}]}},{"value":"Q1346992","rank":"normal","qualifiers":{"P580":[{"time":"1952-02-06","timezone":0,"before":0,"after":0,"precision":11,"calendarmodel":"http://www.wikidata.org/entity/Q1985727"}],"P1366":["Q43274"],"P582":[{"time":"2022-09-08","timezone":0,"before":0,"after":0,"precision":11,"calendarmodel":"http://www.wikidata.org/entity/Q1985727"}]}},{"value":"Q2985714","rank":"normal","qualifiers":{"P1001":["Q16"],"P1393":["Q390776"],"P580":[{"time":"1952","timezone":0,"before":0,"after":0,"precision":9,"calendarmodel":"http://www.wikidata.org/entity/Q1985727"}]}},{"value":"Q1370385","rank":"normal","qualifiers":{"P642":["Q739941"],"P580":[{"time":"1936-12-11","timezone":0,"before":0,"after":0,"precision":11,"calendarmodel":"http://www.wikidata.org/entity/Q1985727"}],"P582":[{"time":"1952-02-06","timezone":0,"before":0,"after":0,"precision":11,"calendarmodel":"http://www.wikidata.org/entity/Q1985727"}],"P1534":["Q3832870"]}}],"P511":[{"value":"Q669458","rank":"preferred","qualifiers":{"P580":[{"time":"1952-02-06","timezone":0,"before":0,"after":0,"precision":11,"calendarmodel":"http://www.wikidata.org/entity/Q1985727"}]}},{"value":"Q1252328","rank":"normal","qualifiers":{"P580":[{"time":"1926-04-21","timezone":0,"before":0,"after":0,"precision":11,"calendarmodel":"http://www.wikidata.org/entity/Q1985727"}],"P582":[{"time":"1952-02-06","timezone":0,"before":0,"after":0,"precision":11,"calendarmodel":"http://www.wikidata.org/entity/Q1985727"}]}}],"P2561":[],"P1950":[],"P5056":[],"P2652":[],"P69":[],"P102":[],"P3602":[],"P3448":[],"P451":[],"P1290":[],"P8810":[],"P1038":[]},"sitelinks":{"acewiki":"Elizabeth II","afwiki":"Elizabeth II van die Verenigde Koninkryk","alswiki":"Elisabeth II.","amiwiki":"Elizabeth II","amwiki":"ንግሥት ኤልሣቤጥ ዳግማዊት","angwiki":"Elisabeþ II","anwiki":"Isabel II d'o Reino Uniu","arcwiki":"ܐܠܝܙܒܬ ܬܪܝܢܝܬܐ","arwiki":"إليزابيث الثانية","arywiki":"إيليزابيط التانية","arzwiki":"اليزابيث التانيه","astwiki":"Sabela II del Reinu Xuníu","avwiki":"Элизабет II","azbwiki":"ایکینجی الیزابت","azwiki":"II Elizabet","azwikiquote":"II Elizabet","banwiki":"Elizabeth II","bat_smgwiki":"Elžbieta II","bawiki":"Елизавета II","bclwiki":"Isabel II","be_x_oldwiki":"Лізавета II","bewiki":"Лізавета II","bgwiki":"Елизабет II","bgwikiquote":"Елизабет II","bhwiki":"एलिजाबेथ II","biwiki":"Elisabet II","bjnwiki":"Elizabeth II matan Britania Raya","blkwiki":"ဒုတိယ အဲလီသဘဲတ်","bnwiki":"দ্বিতীয় এলিজাবেথ","brwiki":"Elesbed II","bswiki":"Elizabeta II","bxrwiki":"II Елизавета","cawiki":"Elisabet II del Regne Unit","cawikiquote":"Elisabet II del Regne Unit","cbk_zamwiki":"Reina Elizabeth, el aca-segundo","cdowiki":"Elizabeth 2-sié","cebwiki":"Elizabeth II sa Hiniusang Gingharian","cewiki":"II Елизавета","ckbwiki":"ئێلیزابێتی دووەم","commonswiki":"Queen Elizabeth II","cowiki":"Elisabetta II","crhwiki":"II Elizabet","cswiki":"Alžběta II.","cswikiquote":"Alžběta II.","cvwiki":"Елизавета II","cywiki":"Elisabeth II","dagwiki":"Elizabeth II","dawiki":"Elizabeth 2. af Storbritannien","dewiki":"Elisabeth II.","dewikinews":"Kategorie:Elizabeth II. (Commonwealth)","dinwiki":"Elidhabeth II","diqwiki":"Elizabeth II","elwiki":"Ελισάβετ Β΄ του Ηνωμένου Βασιλείου","enwiki":"Elizabeth II","enwikibooks":"UK Constitution and Government/British Monarchs/Elizabeth II of the United Kingdom","enwikinews":"Category:Queen Elizabeth II","enwikiquote":"Elizabeth II","enwikisource":"Author:Elizabeth II","eowiki":"Elizabeto la 2-a (Britio)","eowikinews":"Kategorio:Elizabeto la 2-a (Britio)","eswiki":"Isabel II del Reino Unido","eswikinews":"Categoría:Isabel II del Reino Unido","eswikiquote":"Isabel II del Reino Unido","etwiki":"Elizabeth II","etwikiquote":"Elizabeth II","euwiki":"Elizabeth II.a Erresuma Batukoa","extwiki":"Isabel II del Réinu Uniu","fawiki":"الیزابت دوم","fawikiquote":"ملکه الیزابت دوم","fiu_vrowiki":"Kuningaimänd Elizabeth II","fiwiki":"Elisabet II","fiwikiquote":"Elizabeth II","fowiki":"Elisabeth II drotning","frpwiki":"Èlisabèt II","frrwiki":"Elisabeth II.","frwiki":"Élisabeth II","frwikinews":"Catégorie:Élisabeth II du Royaume-Uni","furwiki":"Regjine Bete II","fywiki":"Elizabeth II fan it Feriene Keninkryk","gawiki":"Eilís II na Ríochta Aontaithe","gdwiki":"Bànrigh Ealasaid II","glwiki":"Isabel II do Reino Unido","gnwiki":"Isabel II Tavetã Joaju pegua","gomwiki":"Queen Elizabeth II","gvwiki":"Ealisaid II y Reeriaght Unnaneysit","hakwiki":"Elizabeth 2-sṳ","hawiki":"Elizabeth II","hawwiki":"Elikapeka II","hewiki":"אליזבת השנייה, מלכת הממלכה המאוחדת","hewikiquote":"אליזבת השנייה, מלכת הממלכה המאוחדת","hiwiki":"एलिज़ाबेथ द्वितीय","hrwiki":"Elizabeta II.","hsbwiki":"Hilžbjeta II.","htwiki":"Elizabeth II","huwiki":"II. Erzsébet brit királynő","hywiki":"Եղիսաբեթ II","hywwiki":"Էլիզապէթ Բ.","iawiki":"Elisabeth II del Regno Unite","idwiki":"Elizabeth II dari Britania Raya","iewiki":"Elisabeth II","igwiki":"Elizabeth II","ilowiki":"Isabel II","iowiki":"Elizabeth la 2ma dil Unionita Rejio","iswiki":"Elísabet 2. Bretadrottning","itwiki":"Elisabetta II del Regno Unito","itwikiquote":"Elisabetta II del Regno Unito","jawiki":"エリザベス2世","jvwiki":"Elizabeth II saking Britani Agung","kabwiki":"Elizabeth II","kawiki":"ელისაბედ II","kbpwiki":"Elizabeth 2","kcgwiki":"A̱li̱za̱ba̱t II","kkwiki":"II Елизабет","kmwiki":"សម្តេចព្រះរាជិនីនាថអេលីហ្សាប៊ែតទី ២ នៃសហរាជាណាចក្រ","knwiki":"ಎರಡನೇ ಎಲಿಜಬೆಥ್","kowiki":"엘리자베스 2세","kowikisource":"저자:엘리자베스 2세","kuwiki":"Elizabeth II","kwwiki":"Elisabeth II","kywiki":"Елизавета II","lawiki":"Elizabeth II (regina Britanniarum)","lbwiki":"Elizabeth II.","lfnwiki":"Elizabeth 2","liwiki":"Elizabeth II","lmowiki":"Lisabetta II del Regn Unii","lowiki":"ສົມເດັດພະລາຊິນີນາດເອລີຊາແບັດທີ 2 ແຫ່ງສະຫະລາຊະອານາຈັກ","ltwiki":"Elžbieta II","ltwikiquote":"Elžbieta II","lvwiki":"Elizabete II Vindzora","maiwiki":"एलिजाबेथ द्वितीय","mgwiki":"Elizabeth II","miwiki":"Irihāpeti te Tuarua","mkwiki":"Елизабета II","mlwiki":"എലിസബത്ത് II","mniwiki":"ꯑꯦꯂꯤꯖꯥꯕꯦꯊ ꯲","mnwiki":"II Элизабет","mnwwiki":"ဨလဳသဗေတ် ဒုတိယ","mrwiki":"दुसरी एलिझाबेथ","mswiki":"Elizabeth II","mtwiki":"Eliżabetta II","mywiki":"ဒုတိယ အယ်လီဇဘက်","nahwiki":"Cihuatlahtoani Elizabeth II","napwiki":"Elisabetta II d''o Regno Aunito","nawiki":"Elizabeth II","ndswiki":"Elisabeth II. (Windsor)","newiki":"एलिजाबेथ द्वितीय","newwiki":"संयुक्त अधिराज्ययाम्ह एलिजाबेथ निम्ह","nlwiki":"Elizabeth II van het Verenigd Koninkrijk","nlwikinews":"Categorie:Elizabeth II van het Verenigd Koninkrijk","nlwikiquote":"Elizabeth II van het Verenigd Koninkrijk","nnwiki":"Elizabeth II av Storbritannia","novwiki":"Elisabeth II","nowiki":"Elizabeth II av Storbritannia","nrmwiki":"Lîzabé II du Rouoyaume Unni","nvwiki":"Kwį́į́n Elizabeth II","nywiki":"Elizabeth II","ocwiki":"Elisabèt II del Reialme Unit","oswiki":"Елизаветæ II","papwiki":"Elizabeth II","pawiki":"ਐਲਿਜ਼ਾਬੈਥ II","pcdwiki":"HM Queen Elizabeth II","pihwiki":"Elisabeth II","plwiki":"Elżbieta II","plwikiquote":"Elżbieta II","pmswiki":"Elisabeta II dël Regn Unì","pnbwiki":"الزبتھ II","pswiki":"دوهمه ملکه الیزابت","ptwiki":"Isabel II do Reino Unido","ptwikinews":"Categoria:Elizabeth II","ptwikiquote":"Isabel II do Reino Unido","quwiki":"Elisabeth II","roa_tarawiki":"Lesabbètte II d'u Regne Aunìte","rowiki":"Elisabeta a II-a","ruwiki":"Елизавета II","ruwikinews":"Категория:Елизавета II","ruwikiquote":"Елизавета II","sawiki":"एलिज़बेथ २","scnwiki":"Elisabetta II dû Regnu Unitu","scowiki":"Elizabeth II","sdwiki":"ايلزبٿ ٻين (برطانيا)","sewiki":"Elizabeth II","shnwiki":"ဢႄးလိၸ်ႉၸပႅတ်ႉ ထူၼ်ႈသွင်","shwiki":"Elizabeta II","simplewiki":"Elizabeth II","simplewikiquote":"Elizabeth II of the United Kingdom","siwiki":"දෙවන එලිසබෙත් රැජිණ","skwiki":"Alžbeta II.","slwiki":"Elizabeta II. Britanska","smnwiki":"Elizabeth II","smwiki":"Masiofo Elisapeta II","sowiki":"Elizabeth II","sqwiki":"Elizabeta II","srwiki":"Елизабета II","srwikinews":"Категорија:Елизабета II","srwikiquote":"Елизабета II","sswiki":"Indlovukazi Elizabeth II","svwiki":"Elizabeth II av Storbritannien","swwiki":"Elizabeth II wa Uingereza","szlwiki":"Elizabeth II","szywiki":"Elizabeth II","tawiki":"ஐக்கிய இராச்சியத்தின் இரண்டாம் எலிசபெத்","taywiki":"Elizabeth II","tewiki":"ఎలిజబెత్ II","tgwiki":"Елизаветаи II","thwiki":"สมเด็จพระราชินีนาถเอลิซาเบธที่ 2 แห่งสหราชอาณาจักร","thwikiquote":"สมเด็จพระราชินีนาถเอลิซาเบธที่ 2 แห่งสหราชอาณาจักร","tkwiki":"Elizabeth II","tlwiki":"Elizabeth II","tnwiki":"Elizabeth II","towiki":"ʻElisapesi II","tpiwiki":"Elisabet II","trvwiki":"Elizabeth II","trwiki":"II. Elizabeth","trwikiquote":"II. Elizabeth","ttwiki":"Елизавета II","tumwiki":"Elizabeth II","ugwiki":"ئېلىزابېت II","ukwiki":"Єлизавета II","ukwikiquote":"Єлизавета II","urwiki":"ایلزبتھ دؤم","urwikiquote":"ملکہ ایلزبتھ دؤم","uzwiki":"Elizabeth II","vecwiki":"Elisabeta II del Regno Unio","vepwiki":"Elizavet II","viwiki":"Elizabeth II","vowiki":"Elizabeth IIid","warwiki":"Elizabeth II","wuuwiki":"伊丽莎白两世","xmfwiki":"ელისაბედ II","yiwiki":"עליזאבעט די צווייטע","yowiki":"Elisabeti Kejì","zawiki":"Yihlisahbwz Ngeih Seiq","zeawiki":"Elizabeth II","zh_classicalwiki":"伊莉莎白二世","zh_min_nanwiki":"Elizabeth 2-sè","zh_yuewiki":"伊利沙伯二世","zhwiki":"伊丽莎白二世","zhwikiquote":"伊麗莎白二世","zuwiki":"Elizabeth II"}}
